Workbook

Sheet Master_Data_Features
B2: Feature_ID | C2: Feature_Name | D2: Agent_Type | E2: Category | F2: Quarter_Planned | G2: Replicability_Score | H2: Primary_Client | I2: Additional_Clients | J2: Platform_vs_Custom | K2: ARR_Amount | L2: Revenue_Type | M2: Contract_Status | N2: Pipeline_Stage | O2: Conversion_Probability_% | P2: Current_Status | Q2: Completion_% | R2: Target_Completion_Date | S2: Effort_Estimate_Weeks | T2: Revenue_at_Risk | U2: Priority_Score | V2: Engineering_Notes | W2: Management_Notes | X2: Client_Count | Y2: Deal_Close_Date | Z2: Days_to_Close | AA2: Multi_Client_Benefit | AB2: Effort_Estimate_Weeks | AC2: Effort_T-Shirt_Size | AD2: Engineering_Complexity | AE2: Dependencies | AF2: Team_Required | AG2: Priority_Score | AH2: Priority_Tier | AI2: Revenue_Impact_Type | AJ2: Weighted_ARR | AK2: Assigned_To | AL2: Sprint_Assignment | AM2: JIRA_Ticket_Count | AN2: Created_Date | AO2: Target_Start_Date | AP2: Sales_Notes | AQ2: Manual_Override | AR2: Manual_Override_Score | AS2: Artemis_Focus | AT2: PRD_Status | AU2: Epic_in_JIRA
B3: F-001 | C3: LLM-Enhanced Extraction | D3: Platform (All Agents) | E3: Platform Improvements | F3: Q4 2025 | G3: 5 | H3: Multiple | I3: 0 | J3: Platform Enhancement | X3: =IF(H3="Multiple",IF(ISBLANK(I3),1,LEN(I3)-LEN(SUBSTITUTE(I3,",",""))+1),IF(NOT(ISBLANK(I3)),LEN(I3)-LEN(SUBSTITUTE(I3,",",""))+2,1)) -> 1 | Z3: =IF(NOT(ISBLANK(Y3)),Y3-TODAY(),"") | AG3: =IF(AND(NOT(ISBLANK(K3)),NOT(ISBLANK(G3)),NOT(ISBLANK(O3)),NOT(ISBLANK(AB3)),AB3>0),(K3*G3*(O3/100))/AB3,0) -> 0 | AH3: =IF(T3="Yes","Tier 0: Emergency",IF(AG3>=100,"Tier 1: Fast Track",IF(AG3>=50,"Tier 2: Standard Delivery",IF(AG3>=10,"Tier 3: Custom Engagement","Tier 4: Backlog")))) -> Tier 4: Backlog | AI3: =IF(T3="Yes","Negative (Risk of Loss)",IF(L3="Retention/Risk of Loss","Negative (Risk of Loss)",IF(AND(K3>0,OR(L3="New Contract",L3="Expansion")),"Positive (New Revenue)","Neutral (Internal/Platform)"))) -> Neutral (Internal/Platform) | AJ3: =IF(NOT(ISBLANK(K3)),K3*(O3/100),0) -> 0 | AP3: =COUNTIF(Master_Data_JIRA_Tickets!I:I,B3) -> 0 | AS3: Yes | AT3: In Progress | AU3: Yes
B4: F-002 | C4: Client Agent Interaction Enhancements | D4: Platform (All Agents) | E4: Platform Improvements | F4: Q4 2025 | G4: 5 | H4: Multiple | I4: 0 | J4: Platform Enhancement | X4: =IF(H4="Multiple",IF(ISBLANK(I4),1,LEN(I4)-LEN(SUBSTITUTE(I4,",",""))+1),IF(NOT(ISBLANK(I4)),LEN(I4)-LEN(SUBSTITUTE(I4,",",""))+2,1)) -> 1 | Z4: =IF(NOT(ISBLANK(Y4)),Y4-TODAY(),"") | AG4: =IF(AND(NOT(ISBLANK(K4)),NOT(ISBLANK(G4)),NOT(ISBLANK(O4)),NOT(ISBLANK(AB4)),AB4>0),(K4*G4*(O4/100))/AB4,0) -> 0 | AH4: =IF(T4="Yes","Tier 0: Emergency",IF(AG4>=100,"Tier 1: Fast Track",IF(AG4>=50,"Tier 2: Standard Delivery",IF(AG4>=10,"Tier 3: Custom Engagement","Tier 4: Backlog")))) -> Tier 4: Backlog | AI4: =IF(T4="Yes","Negative (Risk of Loss)",IF(L4="Retention/Risk of Loss","Negative (Risk of Loss)",IF(AND(K4>0,OR(L4="New Contract",L4="Expansion")),"Positive (New Revenue)","Neutral (Internal/Platform)"))) -> Neutral (Internal/Platform) | AJ4: =IF(NOT(ISBLANK(K4)),K4*(O4/100),0) -> 0 | AP4: =COUNTIF(Master_Data_JIRA_Tickets!I:I,B4) -> 0 | AS4: No | AT4: Not Started | AU4: No
B5: F-003 | C5: DeepSee Service Fabric Internal Enhancements | D5: Platform (All Agents) | E5: Core Infrastructure | F5: Q4 2025 | G5: 5 | H5: Internal | I5: 0 | J5: Platform Enhancement | X5: =IF(H5="Multiple",IF(ISBLANK(I5),1,LEN(I5)-LEN(SUBSTITUTE(I5,",",""))+1),IF(NOT(ISBLANK(I5)),LEN(I5)-LEN(SUBSTITUTE(I5,",",""))+2,1)) -> 2 | Z5: =IF(NOT(ISBLANK(Y5)),Y5-TODAY(),"") | AG5: =IF(AND(NOT(ISBLANK(K5)),NOT(ISBLANK(G5)),NOT(ISBLANK(O5)),NOT(ISBLANK(AB5)),AB5>0),(K5*G5*(O5/100))/AB5,0) -> 0 | AH5: =IF(T5="Yes","Tier 0: Emergency",IF(AG5>=100,"Tier 1: Fast Track",IF(AG5>=50,"Tier 2: Standard Delivery",IF(AG5>=10,"Tier 3: Custom Engagement","Tier 4: Backlog")))) -> Tier 4: Backlog | AI5: =IF(T5="Yes","Negative (Risk of Loss)",IF(L5="Retention/Risk of Loss","Negative (Risk of Loss)",IF(AND(K5>0,OR(L5="New Contract",L5="Expansion")),"Positive (New Revenue)","Neutral (Internal/Platform)"))) -> Neutral (Internal/Platform) | AJ5: =IF(NOT(ISBLANK(K5)),K5*(O5/100),0) -> 0 | AP5: =COUNTIF(Master_Data_JIRA_Tickets!I:I,B5) -> 0 | AS5: No | AT5: Not Started | AU5: No
B6: F-004 | C6: Retention Prediction UI | D6: Platform (Analytics) | E6: Platform Improvements | F6: Q4 2025 | G6: 5 | H6: Multiple | I6: 0 | J6: Platform Enhancement | X6: =IF(H6="Multiple",IF(ISBLANK(I6),1,LEN(I6)-LEN(SUBSTITUTE(I6,",",""))+1),IF(NOT(ISBLANK(I6)),LEN(I6)-LEN(SUBSTITUTE(I6,",",""))+2,1)) -> 1 | Z6: =IF(NOT(ISBLANK(Y6)),Y6-TODAY(),"") | AG6: =IF(AND(NOT(ISBLANK(K6)),NOT(ISBLANK(G6)),NOT(ISBLANK(O6)),NOT(ISBLANK(AB6)),AB6>0),(K6*G6*(O6/100))/AB6,0) -> 0 | AH6: =IF(T6="Yes","Tier 0: Emergency",IF(AG6>=100,"Tier 1: Fast Track",IF(AG6>=50,"Tier 2: Standard Delivery",IF(AG6>=10,"Tier 3: Custom Engagement","Tier 4: Backlog")))) -> Tier 4: Backlog | AI6: =IF(T6="Yes","Negative (Risk of Loss)",IF(L6="Retention/Risk of Loss","Negative (Risk of Loss)",IF(AND(K6>0,OR(L6="New Contract",L6="Expansion")),"Positive (New Revenue)","Neutral (Internal/Platform)"))) -> Neutral (Internal/Platform) | AJ6: =IF(NOT(ISBLANK(K6)),K6*(O6/100),0) -> 0 | AP6: =COUNTIF(Master_Data_JIRA_Tickets!I:I,B6) -> 0 | AS6: No | AT6: Not Started | AU6: No
B7: F-005 | C7: Double-click to view dashboard messages | D7: Platform (Analytics) | E7: Platform Improvements | F7: Q4 2025 | G7: 5 | H7: Multiple | I7: 0 | J7: Platform Enhancement | X7: =IF(H7="Multiple",IF(ISBLANK(I7),1,LEN(I7)-LEN(SUBSTITUTE(I7,",",""))+1),IF(NOT(ISBLANK(I7)),LEN(I7)-LEN(SUBSTITUTE(I7,",",""))+2,1)) -> 1 | Z7: =IF(NOT(ISBLANK(Y7)),Y7-TODAY(),"") | AG7: =IF(AND(NOT(ISBLANK(K7)),NOT(ISBLANK(G7)),NOT(ISBLANK(O7)),NOT(ISBLANK(AB7)),AB7>0),(K7*G7*(O7/100))/AB7,0) -> 0 | AH7: =IF(T7="Yes","Tier 0: Emergency",IF(AG7>=100,"Tier 1: Fast Track",IF(AG7>=50,"Tier 2: Standard Delivery",IF(AG7>=10,"Tier 3: Custom Engagement","Tier 4: Backlog")))) -> Tier 4: Backlog | AI7: =IF(T7="Yes","Negative (Risk of Loss)",IF(L7="Retention/Risk of Loss","Negative (Risk of Loss)",IF(AND(K7>0,OR(L7="New Contract",L7="Expansion")),"Positive (New Revenue)","Neutral (Internal/Platform)"))) -> Neutral (Internal/Platform) | AJ7: =IF(NOT(ISBLANK(K7)),K7*(O7/100),0) -> 0 | AP7: =COUNTIF(Master_Data_JIRA_Tickets!I:I,B7) -> 0 | AS7: No | AT7: Not Started | AU7: No
B8: F-006 | C8: Simplified Agentic UI Design | D8: Platform (All Agents) | E8: Platform Improvements | F8: Q4 2025 | G8: 5 | H8: Multiple | I8: 0 | J8: Platform Enhancement | X8: =IF(H8="Multiple",IF(ISBLANK(I8),1,LEN(I8)-LEN(SUBSTITUTE(I8,",",""))+1),IF(NOT(ISBLANK(I8)),LEN(I8)-LEN(SUBSTITUTE(I8,",",""))+2,1)) -> 1 | Z8: =IF(NOT(ISBLANK(Y8)),Y8-TODAY(),"") | AG8: =IF(AND(NOT(ISBLANK(K8)),NOT(ISBLANK(G8)),NOT(ISBLANK(O8)),NOT(ISBLANK(AB8)),AB8>0),(K8*G8*(O8/100))/AB8,0) -> 0 | AH8: =IF(T8="Yes","Tier 0: Emergency",IF(AG8>=100,"Tier 1: Fast Track",IF(AG8>=50,"Tier 2: Standard Delivery",IF(AG8>=10,"Tier 3: Custom Engagement","Tier 4: Backlog")))) -> Tier 4: Backlog | AI8: =IF(T8="Yes","Negative (Risk of Loss)",IF(L8="Retention/Risk of Loss","Negative (Risk of Loss)",IF(AND(K8>0,OR(L8="New Contract",L8="Expansion")),"Positive (New Revenue)","Neutral (Internal/Platform)"))) -> Neutral (Internal/Platform) | AJ8: =IF(NOT(ISBLANK(K8)),K8*(O8/100),0) -> 0 | AP8: =COUNTIF(Master_Data_JIRA_Tickets!I:I,B8) -> 0 | AS8: Yes | AT8: In Progress | AU8: Yes
B9: F-007 | C9: Matching Engine UI | D9: Matching Engine | E9: Platform Improvements | F9: Q4 2025 | G9: 4 | H9: Multiple | I9: 0 | J9: Platform Enhancement | X9: =IF(H9="Multiple",IF(ISBLANK(I9),1,LEN(I9)-LEN(SUBSTITUTE(I9,",",""))+1),IF(NOT(ISBLANK(I9)),LEN(I9)-LEN(SUBSTITUTE(I9,",",""))+2,1)) -> 1 | Z9: =IF(NOT(ISBLANK(Y9)),Y9-TODAY(),"") | AG9: =IF(AND(NOT(ISBLANK(K9)),NOT(ISBLANK(G9)),NOT(ISBLANK(O9)),NOT(ISBLANK(AB9)),AB9>0),(K9*G9*(O9/100))/AB9,0) -> 0 | AH9: =IF(T9="Yes","Tier 0: Emergency",IF(AG9>=100,"Tier 1: Fast Track",IF(AG9>=50,"Tier 2: Standard Delivery",IF(AG9>=10,"Tier 3: Custom Engagement","Tier 4: Backlog")))) -> Tier 4: Backlog | AI9: =IF(T9="Yes","Negative (Risk of Loss)",IF(L9="Retention/Risk of Loss","Negative (Risk of Loss)",IF(AND(K9>0,OR(L9="New Contract",L9="Expansion")),"Positive (New Revenue)","Neutral (Internal/Platform)"))) -> Neutral (Internal/Platform) | AJ9: =IF(NOT(ISBLANK(K9)),K9*(O9/100),0) -> 0 | AP9: =COUNTIF(Master_Data_JIRA_Tickets!I:I,B9) -> 0 | AS9: No | AT9: Not Started | AU9: No
B10: F-008 | C10: Information Graph Enhanced Infrastructure | D10: Platform (All Agents) | E10: Core Infrastructure | F10: Q1 2026 | G10: 5 | H10: Multiple | I10: 0 | J10: Platform Enhancement | X10: =IF(H10="Multiple",IF(ISBLANK(I10),1,LEN(I10)-LEN(SUBSTITUTE(I10,",",""))+1),IF(NOT(ISBLANK(I10)),LEN(I10)-LEN(SUBSTITUTE(I10,",",""))+2,1)) -> 1 | Z10: =IF(NOT(ISBLANK(Y10)),Y10-TODAY(),"") | AG10: =IF(AND(NOT(ISBLANK(K10)),NOT(ISBLANK(G10)),NOT(ISBLANK(O10)),NOT(ISBLANK(AB10)),AB10>0),(K10*G10*(O10/100))/AB10,0) -> 0 | AH10: =IF(T10="Yes","Tier 0: Emergency",IF(AG10>=100,"Tier 1: Fast Track",IF(AG10>=50,"Tier 2: Standard Delivery",IF(AG10>=10,"Tier 3: Custom Engagement","Tier 4: Backlog")))) -> Tier 4: Backlog | AI10: =IF(T10="Yes","Negative (Risk of Loss)",IF(L10="Retention/Risk of Loss","Negative (Risk of Loss)",IF(AND(K10>0,OR(L10="New Contract",L10="Expansion")),"Positive (New Revenue)","Neutral (Internal/Platform)"))) -> Neutral (Internal/Platform) | AJ10: =IF(NOT(ISBLANK(K10)),K10*(O10/100),0) -> 0 | AP10: =COUNTIF(Master_Data_JIRA_Tickets!I:I,B10) -> 0 | AS10: Yes | AT10: In Progress | AU10: Yes
B11: F-009 | C11: Enhanced Agent Outcome Reasoning and Planning | D11: Platform (All Agents) | E11: Platform Improvements | F11: Q1 2026 | G11: 5 | H11: Multiple | I11: 0 | J11: Platform Enhancement | X11: =IF(H11="Multiple",IF(ISBLANK(I11),1,LEN(I11)-LEN(SUBSTITUTE(I11,",",""))+1),IF(NOT(ISBLANK(I11)),LEN(I11)-LEN(SUBSTITUTE(I11,",",""))+2,1)) -> 1 | Z11: =IF(NOT(ISBLANK(Y11)),Y11-TODAY(),"") | AG11: =IF(AND(NOT(ISBLANK(K11)),NOT(ISBLANK(G11)),NOT(ISBLANK(O11)),NOT(ISBLANK(AB11)),AB11>0),(K11*G11*(O11/100))/AB11,0) -> 0 | AH11: =IF(T11="Yes","Tier 0: Emergency",IF(AG11>=100,"Tier 1: Fast Track",IF(AG11>=50,"Tier 2: Standard Delivery",IF(AG11>=10,"Tier 3: Custom Engagement","Tier 4: Backlog")))) -> Tier 4: Backlog | AI11: =IF(T11="Yes","Negative (Risk of Loss)",IF(L11="Retention/Risk of Loss","Negative (Risk of Loss)",IF(AND(K11>0,OR(L11="New Contract",L11="Expansion")),"Positive (New Revenue)","Neutral (Internal/Platform)"))) -> Neutral (Internal/Platform) | AJ11: =IF(NOT(ISBLANK(K11)),K11*(O11/100),0) -> 0 | AP11: =COUNTIF(Master_Data_JIRA_Tickets!I:I,B11) -> 0 | AS11: Yes | AT11: In Progress | AU11: Yes
B12: F-010 | C12: Inference / Training speed improvements | D12: Platform (All Agents) | E12: Core Infrastructure | F12: Q1 2026 | G12: 5 | H12: Multiple | I12: 0 | J12: Platform Enhancement | X12: =IF(H12="Multiple",IF(ISBLANK(I12),1,LEN(I12)-LEN(SUBSTITUTE(I12,",",""))+1),IF(NOT(ISBLANK(I12)),LEN(I12)-LEN(SUBSTITUTE(I12,",",""))+2,1)) -> 1 | Z12: =IF(NOT(ISBLANK(Y12)),Y12-TODAY(),"") | AG12: =IF(AND(NOT(ISBLANK(K12)),NOT(ISBLANK(G12)),NOT(ISBLANK(O12)),NOT(ISBLANK(AB12)),AB12>0),(K12*G12*(O12/100))/AB12,0) -> 0 | AH12: =IF(T12="Yes","Tier 0: Emergency",IF(AG12>=100,"Tier 1: Fast Track",IF(AG12>=50,"Tier 2: Standard Delivery",IF(AG12>=10,"Tier 3: Custom Engagement","Tier 4: Backlog")))) -> Tier 4: Backlog | AI12: =IF(T12="Yes","Negative (Risk of Loss)",IF(L12="Retention/Risk of Loss","Negative (Risk of Loss)",IF(AND(K12>0,OR(L12="New Contract",L12="Expansion")),"Positive (New Revenue)","Neutral (Internal/Platform)"))) -> Neutral (Internal/Platform) | AJ12: =IF(NOT(ISBLANK(K12)),K12*(O12/100),0) -> 0 | AP12: =COUNTIF(Master_Data_JIRA_Tickets!I:I,B12) -> 0 | AS12: Yes | AT12: In Progress | AU12: Yes
B13: F-011 | C13: Activity Tracing Across Agents | D13: Platform (Analytics) | E13: Platform Improvements | F13: Q1 2026 | G13: 5 | H13: Multiple | I13: 0 | J13: Platform Enhancement | X13: =IF(H13="Multiple",IF(ISBLANK(I13),1,LEN(I13)-LEN(SUBSTITUTE(I13,",",""))+1),IF(NOT(ISBLANK(I13)),LEN(I13)-LEN(SUBSTITUTE(I13,",",""))+2,1)) -> 1 | Z13: =IF(NOT(ISBLANK(Y13)),Y13-TODAY(),"") | AG13: =IF(AND(NOT(ISBLANK(K13)),NOT(ISBLANK(G13)),NOT(ISBLANK(O13)),NOT(ISBLANK(AB13)),AB13>0),(K13*G13*(O13/100))/AB13,0) -> 0 | AH13: =IF(T13="Yes","Tier 0: Emergency",IF(AG13>=100,"Tier 1: Fast Track",IF(AG13>=50,"Tier 2: Standard Delivery",IF(AG13>=10,"Tier 3: Custom Engagement","Tier 4: Backlog")))) -> Tier 4: Backlog | AI13: =IF(T13="Yes","Negative (Risk of Loss)",IF(L13="Retention/Risk of Loss","Negative (Risk of Loss)",IF(AND(K13>0,OR(L13="New Contract",L13="Expansion")),"Positive (New Revenue)","Neutral (Internal/Platform)"))) -> Neutral (Internal/Platform) | AJ13: =IF(NOT(ISBLANK(K13)),K13*(O13/100),0) -> 0 | AP13: =COUNTIF(Master_Data_JIRA_Tickets!I:I,B13) -> 0 | AS13: No | AT13: Not Started | AU13: No
B14: F-012 | C14: Exception Prediction | D14: Platform (Analytics) | E14: Platform Improvements | F14: Q1 2026 | G14: 5 | H14: Multiple | I14: 0 | J14: Platform Enhancement | X14: =IF(H14="Multiple",IF(ISBLANK(I14),1,LEN(I14)-LEN(SUBSTITUTE(I14,",",""))+1),IF(NOT(ISBLANK(I14)),LEN(I14)-LEN(SUBSTITUTE(I14,",",""))+2,1)) -> 1 | Z14: =IF(NOT(ISBLANK(Y14)),Y14-TODAY(),"") | AG14: =IF(AND(NOT(ISBLANK(K14)),NOT(ISBLANK(G14)),NOT(ISBLANK(O14)),NOT(ISBLANK(AB14)),AB14>0),(K14*G14*(O14/100))/AB14,0) -> 0 | AH14: =IF(T14="Yes","Tier 0: Emergency",IF(AG14>=100,"Tier 1: Fast Track",IF(AG14>=50,"Tier 2: Standard Delivery",IF(AG14>=10,"Tier 3: Custom Engagement","Tier 4: Backlog")))) -> Tier 4: Backlog | AI14: =IF(T14="Yes","Negative (Risk of Loss)",IF(L14="Retention/Risk of Loss","Negative (Risk of Loss)",IF(AND(K14>0,OR(L14="New Contract",L14="Expansion")),"Positive (New Revenue)","Neutral (Internal/Platform)"))) -> Neutral (Internal/Platform) | AJ14: =IF(NOT(ISBLANK(K14)),K14*(O14/100),0) -> 0 | AP14: =COUNTIF(Master_Data_JIRA_Tickets!I:I,B14) -> 0 | AS14: No | AT14: Not Started | AU14: No
... B27: F-025 | C27: Enhanced Testing Suite UI Implementation | D27: Platform (All Agents) | E27: Platform Improvements | F27: Q3 2026 | G27: 5 | H27: Multiple | I27: 0 | J27: Platform Enhancement | X27: =IF(H27="Multiple",IF(ISBLANK(I27),1,LEN(I27)-LEN(SUBSTITUTE(I27,",",""))+1),IF(NOT(ISBLANK(I27)),LEN(I27)-LEN(SUBSTITUTE(I27,",",""))+2,1)) -> 1 | Z27: =IF(NOT(ISBLANK(Y27)),Y27-TODAY(),"") | AG27: =IF(AND(NOT(ISBLANK(K27)),NOT(ISBLANK(G27)),NOT(ISBLANK(O27)),NOT(ISBLANK(AB27)),AB27>0),(K27*G27*(O27/100))/AB27,0) -> 0 | AH27: =IF(T27="Yes","Tier 0: Emergency",IF(AG27>=100,"Tier 1: Fast Track",IF(AG27>=50,"Tier 2: Standard Delivery",IF(AG27>=10,"Tier 3: Custom Engagement","Tier 4: Backlog")))) -> Tier 4: Backlog | AI27: =IF(T27="Yes","Negative (Risk of Loss)",IF(L27="Retention/Risk of Loss","Negative (Risk of Loss)",IF(AND(K27>0,OR(L27="New Contract",L27="Expansion")),"Positive (New Revenue)","Neutral (Internal/Platform)"))) -> Neutral (Internal/Platform) | AJ27: =IF(NOT(ISBLANK(K27)),K27*(O27/100),0) -> 0 | AP27: =COUNTIF(Master_Data_JIRA_Tickets!I:I,B27) -> 0 | AS27: No | AT27: Not Started | AU27: No
B28: F-026 | C28: DTCC Agent Onboarding - Trade Processing Phase 1 | D28: Trade Processing | E28: Client-Specific Work | F28: Q4 2025 | G28: 3 | H28: DTCC | I28: 0 | J28: Client-Specific | K28: 750000 | L28: New Contract | M28: Signed | N28: Closed Won | O28: 1 | Q28: 0.6 | R28: 2025-12-31 | S28: 0 | T28: 0 | U28: 0 | V28: Daily client meetings, high touch | W28: 0 | X28: =IF(H28="Multiple",IF(ISBLANK(I28),1,LEN(I28)-LEN(SUBSTITUTE(I28,",",""))+1),IF(NOT(ISBLANK(I28)),LEN(I28)-LEN(SUBSTITUTE(I28,",",""))+2,1)) -> 2 | Z28: =IF(NOT(ISBLANK(Y28)),Y28-TODAY(),"") | AB28: 12 | AC28: L-Large 8wks | AD28: High | AE28: Service fabric deployment, security audit | AF28: Multiple Teams | AG28: =IF(AND(NOT(ISBLANK(K28)),NOT(ISBLANK(G28)),NOT(ISBLANK(O28)),NOT(ISBLANK(AB28)),AB28>0),(K28*G28*(O28/100))/AB28,0) -> 1875 | AH28: =IF(T28="Yes","Tier 0: Emergency",IF(AG28>=100,"Tier 1: Fast Track",IF(AG28>=50,"Tier 2: Standard Delivery",IF(AG28>=10,"Tier 3: Custom Engagement","Tier 4: Backlog")))) -> Tier 1: Fast Track | AI28: =IF(T28="Yes","Negative (Risk of Loss)",IF(L28="Retention/Risk of Loss","Negative (Risk of Loss)",IF(AND(K28>0,OR(L28="New Contract",L28="Expansion")),"Positive (New Revenue)","Neutral (Internal/Platform)"))) -> Positive (New Revenue) | AJ28: =IF(NOT(ISBLANK(K28)),K28*(O28/100),0) -> 7500 | AP28: =COUNTIF(Master_Data_JIRA_Tickets!I:I,B28) -> 0 | AS28: No | AT28: Complete | AU28: Yes
B29: F-027 | C29: DTCC Agent Onboarding - Trade Processing Phase 2 | D29: Trade Processing | E29: Client-Specific Work | F29: Q1 2026 | G29: 3 | H29: DTCC | I29: 0 | J29: Client-Specific | X29: =IF(H29="Multiple",IF(ISBLANK(I29),1,LEN(I29)-LEN(SUBSTITUTE(I29,",",""))+1),IF(NOT(ISBLANK(I29)),LEN(I29)-LEN(SUBSTITUTE(I29,",",""))+2,1)) -> 2 | Z29: =IF(NOT(ISBLANK(Y29)),Y29-TODAY(),"") | AG29: =IF(AND(NOT(ISBLANK(K29)),NOT(ISBLANK(G29)),NOT(ISBLANK(O29)),NOT(ISBLANK(AB29)),AB29>0),(K29*G29*(O29/100))/AB29,0) -> 0 | AH29: =IF(T29="Yes","Tier 0: Emergency",IF(AG29>=100,"Tier 1: Fast Track",IF(AG29>=50,"Tier 2: Standard Delivery",IF(AG29>=10,"Tier 3: Custom Engagement","Tier 4: Backlog")))) -> Tier 4: Backlog | AI29: =IF(T29="Yes","Negative (Risk of Loss)",IF(L29="Retention/Risk of Loss","Negative (Risk of Loss)",IF(AND(K29>0,OR(L29="New Contract",L29="Expansion")),"Positive (New Revenue)","Neutral (Internal/Platform)"))) -> Neutral (Internal/Platform) | AJ29: =IF(NOT(ISBLANK(K29)),K29*(O29/100),0) -> 0 | AP29: =COUNTIF(Master_Data_JIRA_Tickets!I:I,B29) -> 0 | AS29: No | AT29: Not Started | AU29: No
B30: F-028 | C30: DTCC Agent Onboarding - Core Reconciliation | D30: Core Reconciliation | E30: Client-Specific Work | F30: Q1 2026 | G30: 3 | H30: DTCC | I30: 0 | J30: Client-Specific | X30: =IF(H30="Multiple",IF(ISBLANK(I30),1,LEN(I30)-LEN(SUBSTITUTE(I30,",",""))+1),IF(NOT(ISBLANK(I30)),LEN(I30)-LEN(SUBSTITUTE(I30,",",""))+2,1)) -> 2 | Z30: =IF(NOT(ISBLANK(Y30)),Y30-TODAY(),"") | AG30: =IF(AND(NOT(ISBLANK(K30)),NOT(ISBLANK(G30)),NOT(ISBLANK(O30)),NOT(ISBLANK(AB30)),AB30>0),(K30*G30*(O30/100))/AB30,0) -> 0 | AH30: =IF(T30="Yes","Tier 0: Emergency",IF(AG30>=100,"Tier 1: Fast Track",IF(AG30>=50,"Tier 2: Standard Delivery",IF(AG30>=10,"Tier 3: Custom Engagement","Tier 4: Backlog")))) -> Tier 4: Backlog | AI30: =IF(T30="Yes","Negative (Risk of Loss)",IF(L30="Retention/Risk of Loss","Negative (Risk of Loss)",IF(AND(K30>0,OR(L30="New Contract",L30="Expansion")),"Positive (New Revenue)","Neutral (Internal/Platform)"))) -> Neutral (Internal/Platform) | AJ30: =IF(NOT(ISBLANK(K30)),K30*(O30/100),0) -> 0 | AP30: =COUNTIF(Master_Data_JIRA_Tickets!I:I,B30) -> 0 | AS30: No | AT30: Not Started | AU30: No
B31: F-029 | C31: Broadridge Trade Matching Engine Enhancement | D31: Matching Engine | E31: Client-Specific Work | F31: Q4 2025 | G31: 2 | H31: Broadridge | J31: Client-Specific | X31: =IF(H31="Multiple",IF(ISBLANK(I31),1,LEN(I31)-LEN(SUBSTITUTE(I31,",",""))+1),IF(NOT(ISBLANK(I31)),LEN(I31)-LEN(SUBSTITUTE(I31,",",""))+2,1)) -> 1 | Z31: =IF(NOT(ISBLANK(Y31)),Y31-TODAY(),"") | AG31: =IF(AND(NOT(ISBLANK(K31)),NOT(ISBLANK(G31)),NOT(ISBLANK(O31)),NOT(ISBLANK(AB31)),AB31>0),(K31*G31*(O31/100))/AB31,0) -> 0 | AH31: =IF(T31="Yes","Tier 0: Emergency",IF(AG31>=100,"Tier 1: Fast Track",IF(AG31>=50,"Tier 2: Standard Delivery",IF(AG31>=10,"Tier 3: Custom Engagement","Tier 4: Backlog")))) -> Tier 4: Backlog | AI31: =IF(T31="Yes","Negative (Risk of Loss)",IF(L31="Retention/Risk of Loss","Negative (Risk of Loss)",IF(AND(K31>0,OR(L31="New Contract",L31="Expansion")),"Positive (New Revenue)","Neutral (Internal/Platform)"))) -> Neutral (Internal/Platform) | AJ31: =IF(NOT(ISBLANK(K31)),K31*(O31/100),0) -> 0 | AP31: =COUNTIF(Master_Data_JIRA_Tickets!I:I,B31) -> 0 | AS31: No | AT31: Not Started | AU31: No
B32: F-030 | C32: Broadridge Email Automation Workflow | D32: Email Automation | E32: Client-Specific Work | F32: Q4 2025 | G32: 3 | H32: Broadridge | J32: Client-Specific | K32: 500000 | L32: Expansion | M32: Signed | N32: Closed Won | O32: 1 | X32: =IF(H32="Multiple",IF(ISBLANK(I32),1,LEN(I32)-LEN(SUBSTITUTE(I32,",",""))+1),IF(NOT(ISBLANK(I32)),LEN(I32)-LEN(SUBSTITUTE(I32,",",""))+2,1)) -> 1 | Z32: =IF(NOT(ISBLANK(Y32)),Y32-TODAY(),"") | AB32: 8 | AC32: L-Large 8wks | AD32: Medium | AF32: Backend | AG32: =IF(AND(NOT(ISBLANK(K32)),NOT(ISBLANK(G32)),NOT(ISBLANK(O32)),NOT(ISBLANK(AB32)),AB32>0),(K32*G32*(O32/100))/AB32,0) -> 1875 | AH32: =IF(T32="Yes","Tier 0: Emergency",IF(AG32>=100,"Tier 1: Fast Track",IF(AG32>=50,"Tier 2: Standard Delivery",IF(AG32>=10,"Tier 3: Custom Engagement","Tier 4: Backlog")))) -> Tier 1: Fast Track | AI32: =IF(T32="Yes","Negative (Risk of Loss)",IF(L32="Retention/Risk of Loss","Negative (Risk of Loss)",IF(AND(K32>0,OR(L32="New Contract",L32="Expansion")),"Positive (New Revenue)","Neutral (Internal/Platform)"))) -> Positive (New Revenue) | AJ32: =IF(NOT(ISBLANK(K32)),K32*(O32/100),0) -> 5000 | AP32: =COUNTIF(Master_Data_JIRA_Tickets!I:I,B32) -> 0 | AS32: No | AT32: Complete | AU32: Yes
B33: F-031 | C33: Broadridge Critical Bug Fix - Trade Processing | D33: Trade Processing | E33: Bug Fixes | F33: Q4 2025 | G33: 1 | H33: Broadridge | J33: Client-Specific | K33: -500000 | L33: Retention/Risk of Loss | M33: 0 | N33: 0 | O33: 1 | P33: In Progress | Q33: 0.7 | S33: 1 | T33: Yes | U33: -500000 | V33: Tier 0: Emergency | X33: =IF(H33="Multiple",IF(ISBLANK(I33),1,LEN(I33)-LEN(SUBSTITUTE(I33,",",""))+1),IF(NOT(ISBLANK(I33)),LEN(I33)-LEN(SUBSTITUTE(I33,",",""))+2,1)) -> 1 | Z33: =IF(NOT(ISBLANK(Y33)),Y33-TODAY(),"") | AB33: 1 | AC33: S-Small 2wks | AD33: Low | AF33: Backend | AG33: =IF(AND(NOT(ISBLANK(K33)),NOT(ISBLANK(G33)),NOT(ISBLANK(O33)),NOT(ISBLANK(AB33)),AB33>0),(K33*G33*(O33/100))/AB33,0) -> -5000 | AH33: =IF(T33="Yes","Tier 0: Emergency",IF(AG33>=100,"Tier 1: Fast Track",IF(AG33>=50,"Tier 2: Standard Delivery",IF(AG33>=10,"Tier 3: Custom Engagement","Tier 4: Backlog")))) -> Tier 0: Emergency | AI33: =IF(T33="Yes","Negative (Risk of Loss)",IF(L33="Retention/Risk of Loss","Negative (Risk of Loss)",IF(AND(K33>0,OR(L33="New Contract",L33="Expansion")),"Positive (New Revenue)","Neutral (Internal/Platform)"))) -> Negative (Risk of Loss) | AJ33: =IF(NOT(ISBLANK(K33)),K33*(O33/100),0) -> -5000 | AP33: =COUNTIF(Master_Data_JIRA_Tickets!I:I,B33) -> 0 | AS33: No | AT33: Complete | AU33: Yes
B34: F-032 | C34: JP Morgan Monthly Reconciliation Enhancement | D34: Core Reconciliation | E34: Client-Specific Work | F34: Q1 2026 | G34: 3 | H34: JP Morgan | J34: Client-Specific | X34: =IF(H34="Multiple",IF(ISBLANK(I34),1,LEN(I34)-LEN(SUBSTITUTE(I34,",",""))+1),IF(NOT(ISBLANK(I34)),LEN(I34)-LEN(SUBSTITUTE(I34,",",""))+2,1)) -> 1 | Z34: =IF(NOT(ISBLANK(Y34)),Y34-TODAY(),"") | AG34: =IF(AND(NOT(ISBLANK(K34)),NOT(ISBLANK(G34)),NOT(ISBLANK(O34)),NOT(ISBLANK(AB34)),AB34>0),(K34*G34*(O34/100))/AB34,0) -> 0 | AH34: =IF(T34="Yes","Tier 0: Emergency",IF(AG34>=100,"Tier 1: Fast Track",IF(AG34>=50,"Tier 2: Standard Delivery",IF(AG34>=10,"Tier 3: Custom Engagement","Tier 4: Backlog")))) -> Tier 4: Backlog | AI34: =IF(T34="Yes","Negative (Risk of Loss)",IF(L34="Retention/Risk of Loss","Negative (Risk of Loss)",IF(AND(K34>0,OR(L34="New Contract",L34="Expansion")),"Positive (New Revenue)","Neutral (Internal/Platform)"))) -> Neutral (Internal/Platform) | AJ34: =IF(NOT(ISBLANK(K34)),K34*(O34/100),0) -> 0 | AP34: =COUNTIF(Master_Data_JIRA_Tickets!I:I,B34) -> 0 | AS34: No | AT34: Not Started | AU34: No
B35: F-033 | C35: JP Morgan Security Settlements Optimization | D35: Security Settlements | E35: Client-Specific Work | F35: Q2 2026 | G35: 3 | H35: JP Morgan | J35: Client-Specific | X35: =IF(H35="Multiple",IF(ISBLANK(I35),1,LEN(I35)-LEN(SUBSTITUTE(I35,",",""))+1),IF(NOT(ISBLANK(I35)),LEN(I35)-LEN(SUBSTITUTE(I35,",",""))+2,1)) -> 1 | Z35: =IF(NOT(ISBLANK(Y35)),Y35-TODAY(),"") | AG35: =IF(AND(NOT(ISBLANK(K35)),NOT(ISBLANK(G35)),NOT(ISBLANK(O35)),NOT(ISBLANK(AB35)),AB35>0),(K35*G35*(O35/100))/AB35,0) -> 0 | AH35: =IF(T35="Yes","Tier 0: Emergency",IF(AG35>=100,"Tier 1: Fast Track",IF(AG35>=50,"Tier 2: Standard Delivery",IF(AG35>=10,"Tier 3: Custom Engagement","Tier 4: Backlog")))) -> Tier 4: Backlog | AI35: =IF(T35="Yes","Negative (Risk of Loss)",IF(L35="Retention/Risk of Loss","Negative (Risk of Loss)",IF(AND(K35>0,OR(L35="New Contract",L35="Expansion")),"Positive (New Revenue)","Neutral (Internal/Platform)"))) -> Neutral (Internal/Platform) | AJ35: =IF(NOT(ISBLANK(K35)),K35*(O35/100),0) -> 0 | AP35: =COUNTIF(Master_Data_JIRA_Tickets!I:I,B35) -> 0 | AS35: No | AT35: Not Started | AU35: No
B36: F-034 | C36: Accenture Email Automation Deployment | D36: Email Automation | E36: Client-Specific Work | F36: Q4 2025 | G36: 4 | H36: Accenture | J36: Client-Specific | K36: 1200000 | L36: New Contract | M36: Signed | N36: Closed Won | O36: 1 | X36: =IF(H36="Multiple",IF(ISBLANK(I36),1,LEN(I36)-LEN(SUBSTITUTE(I36,",",""))+1),IF(NOT(ISBLANK(I36)),LEN(I36)-LEN(SUBSTITUTE(I36,",",""))+2,1)) -> 1 | Z36: =IF(NOT(ISBLANK(Y36)),Y36-TODAY(),"") | AB36: 8 | AC36: L-Large 8wks | AD36: Medium | AF36: Multiple Teams | AG36: =IF(AND(NOT(ISBLANK(K36)),NOT(ISBLANK(G36)),NOT(ISBLANK(O36)),NOT(ISBLANK(AB36)),AB36>0),(K36*G36*(O36/100))/AB36,0) -> 6000 | AH36: =IF(T36="Yes","Tier 0: Emergency",IF(AG36>=100,"Tier 1: Fast Track",IF(AG36>=50,"Tier 2: Standard Delivery",IF(AG36>=10,"Tier 3: Custom Engagement","Tier 4: Backlog")))) -> Tier 1: Fast Track | AI36: =IF(T36="Yes","Negative (Risk of Loss)",IF(L36="Retention/Risk of Loss","Negative (Risk of Loss)",IF(AND(K36>0,OR(L36="New Contract",L36="Expansion")),"Positive (New Revenue)","Neutral (Internal/Platform)"))) -> Positive (New Revenue) | AJ36: =IF(NOT(ISBLANK(K36)),K36*(O36/100),0) -> 12000 | AP36: =COUNTIF(Master_Data_JIRA_Tickets!I:I,B36) -> 0 | AS36: No | AT36: Complete | AU36: Yes
B37: F-035 | C37: Accenture Multi-Agent Orchestration | D37: Platform (All Agents) | E37: Client-Specific Work | F37: Q1 2026 | G37: 4 | H37: Accenture | J37: Both | X37: =IF(H37="Multiple",IF(ISBLANK(I37),1,LEN(I37)-LEN(SUBSTITUTE(I37,",",""))+1),IF(NOT(ISBLANK(I37)),LEN(I37)-LEN(SUBSTITUTE(I37,",",""))+2,1)) -> 1 | Z37: =IF(NOT(ISBLANK(Y37)),Y37-TODAY(),"") | AG37: =IF(AND(NOT(ISBLANK(K37)),NOT(ISBLANK(G37)),NOT(ISBLANK(O37)),NOT(ISBLANK(AB37)),AB37>0),(K37*G37*(O37/100))/AB37,0) -> 0 | AH37: =IF(T37="Yes","Tier 0: Emergency",IF(AG37>=100,"Tier 1: Fast Track",IF(AG37>=50,"Tier 2: Standard Delivery",IF(AG37>=10,"Tier 3: Custom Engagement","Tier 4: Backlog")))) -> Tier 4: Backlog | AI37: =IF(T37="Yes","Negative (Risk of Loss)",IF(L37="Retention/Risk of Loss","Negative (Risk of Loss)",IF(AND(K37>0,OR(L37="New Contract",L37="Expansion")),"Positive (New Revenue)","Neutral (Internal/Platform)"))) -> Neutral (Internal/Platform) | AJ37: =IF(NOT(ISBLANK(K37)),K37*(O37/100),0) -> 0 | AP37: =COUNTIF(Master_Data_JIRA_Tickets!I:I,B37) -> 0 | AS37: No | AT37: Not Started | AU37: No
B38: F-036 | C38: SSI Agent Deployment - Colony Bank | D38: Standing Settlement Instructions | E38: Client-Specific Work | F38: Q4 2025 | G38: 5 | H38: Regional Banks | I38: Colony Bank | J38: Platform Enhancement | K38: 200000 | L38: New Contract | M38: Signed | N38: Closed Won | O38: 1 | P38: In Progress | Q38: 0.4 | R38: 2025-12-15 | S38: 6 | X38: =IF(H38="Multiple",IF(ISBLANK(I38),1,LEN(I38)-LEN(SUBSTITUTE(I38,",",""))+1),IF(NOT(ISBLANK(I38)),LEN(I38)-LEN(SUBSTITUTE(I38,",",""))+2,1)) -> 2 | Z38: =IF(NOT(ISBLANK(Y38)),Y38-TODAY(),"") | AB38: 6 | AC38: M-Medium 4wks | AD38: Medium | AF38: Backend | AG38: =IF(AND(NOT(ISBLANK(K38)),NOT(ISBLANK(G38)),NOT(ISBLANK(O38)),NOT(ISBLANK(AB38)),AB38>0),(K38*G38*(O38/100))/AB38,0) -> 1666.6667 | AH38: =IF(T38="Yes","Tier 0: Emergency",IF(AG38>=100,"Tier 1: Fast Track",IF(AG38>=50,"Tier 2: Standard Delivery",IF(AG38>=10,"Tier 3: Custom Engagement","Tier 4: Backlog")))) -> Tier 1: Fast Track | AI38: =IF(T38="Yes","Negative (Risk of Loss)",IF(L38="Retention/Risk of Loss","Negative (Risk of Loss)",IF(AND(K38>0,OR(L38="New Contract",L38="Expansion")),"Positive (New Revenue)","Neutral (Internal/Platform)"))) -> Positive (New Revenue) | AJ38: =IF(NOT(ISBLANK(K38)),K38*(O38/100),0) -> 2000 | AP38: =COUNTIF(Master_Data_JIRA_Tickets!I:I,B38) -> 0 | AS38: No | AT38: Complete | AU38: Yes
B39: F-037 | C39: SSI Agent Deployment - Sunwest Bank | D39: Standing Settlement Instructions | E39: Client-Specific Work | F39: Q1 2026 | G39: 5 | H39: Regional Banks | I39: Sunwest Bank | J39: Platform Enhancement | K39: 180000 | L39: New Contract | M39: Contract Negotiation | N39: Contract Negotiation | O39: 0.8 | X39: =IF(H39="Multiple",IF(ISBLANK(I39),1,LEN(I39)-LEN(SUBSTITUTE(I39,",",""))+1),IF(NOT(ISBLANK(I39)),LEN(I39)-LEN(SUBSTITUTE(I39,",",""))+2,1)) -> 2 | Z39: =IF(NOT(ISBLANK(Y39)),Y39-TODAY(),"") | AB39: 6 | AC39: M-Medium 4wks | AD39: Medium | AF39: Backend | AG39: =IF(AND(NOT(ISBLANK(K39)),NOT(ISBLANK(G39)),NOT(ISBLANK(O39)),NOT(ISBLANK(AB39)),AB39>0),(K39*G39*(O39/100))/AB39,0) -> 1200 | AH39: =IF(T39="Yes","Tier 0: Emergency",IF(AG39>=100,"Tier 1: Fast Track",IF(AG39>=50,"Tier 2: Standard Delivery",IF(AG39>=10,"Tier 3: Custom Engagement","Tier 4: Backlog")))) -> Tier 1: Fast Track | AI39: =IF(T39="Yes","Negative (Risk of Loss)",IF(L39="Retention/Risk of Loss","Negative (Risk of Loss)",IF(AND(K39>0,OR(L39="New Contract",L39="Expansion")),"Positive (New Revenue)","Neutral (Internal/Platform)"))) -> Positive (New Revenue) | AJ39: =IF(NOT(ISBLANK(K39)),K39*(O39/100),0) -> 1440 | AP39: =COUNTIF(Master_Data_JIRA_Tickets!I:I,B39) -> 0 | AS39: No | AT39: Complete | AU39: Yes
B40: F-038 | C40: Vantage Bank Custom Reconciliation (POC) | D40: Core Reconciliation | E40: Client-Specific Work | F40: Q1 2026 | G40: 2 | H40: Regional Banks | I40: Vantage Bank | J40: Client-Specific | K40: 200000 | L40: New Contract | M40: POC | N40: POC | O40: 0.5 | P40: Not Started | S40: 12 | W40: Only proceed if Vantage prepays 50% or signs binding contract | X40: =IF(H40="Multiple",IF(ISBLANK(I40),1,LEN(I40)-LEN(SUBSTITUTE(I40,",",""))+1),IF(NOT(ISBLANK(I40)),LEN(I40)-LEN(SUBSTITUTE(I40,",",""))+2,1)) -> 2 | Z40: =IF(NOT(ISBLANK(Y40)),Y40-TODAY(),"") | AB40: 12 | AC40: XL-Extra Large 12wks+ | AD40: High | AE40: Client requires prepayment | AF40: Backend | AG40: =IF(AND(NOT(ISBLANK(K40)),NOT(ISBLANK(G40)),NOT(ISBLANK(O40)),NOT(ISBLANK(AB40)),AB40>0),(K40*G40*(O40/100))/AB40,0) -> 166.66667 | AH40: =IF(T40="Yes","Tier 0: Emergency",IF(AG40>=100,"Tier 1: Fast Track",IF(AG40>=50,"Tier 2: Standard Delivery",IF(AG40>=10,"Tier 3: Custom Engagement","Tier 4: Backlog")))) -> Tier 1: Fast Track | AI40: =IF(T40="Yes","Negative (Risk of Loss)",IF(L40="Retention/Risk of Loss","Negative (Risk of Loss)",IF(AND(K40>0,OR(L40="New Contract",L40="Expansion")),"Positive (New Revenue)","Neutral (Internal/Platform)"))) -> Positive (New Revenue) | AJ40: =IF(NOT(ISBLANK(K40)),K40*(O40/100),0) -> 1000 | AP40: =COUNTIF(Master_Data_JIRA_Tickets!I:I,B40) -> 0 | AS40: No | AT40: Complete | AU40: Yes
B41: F-039 | C41: Email Automation - Response Generation Enhancement | D41: Email Automation | E41: Platform Improvements | F41: Q2 2026 | G41: 5 | H41: Multiple | I41: 0 | J41: Platform Enhancement | X41: =IF(H41="Multiple",IF(ISBLANK(I41),1,LEN(I41)-LEN(SUBSTITUTE(I41,",",""))+1),IF(NOT(ISBLANK(I41)),LEN(I41)-LEN(SUBSTITUTE(I41,",",""))+2,1)) -> 1 | Z41: =IF(NOT(ISBLANK(Y41)),Y41-TODAY(),"") | AG41: =IF(AND(NOT(ISBLANK(K41)),NOT(ISBLANK(G41)),NOT(ISBLANK(O41)),NOT(ISBLANK(AB41)),AB41>0),(K41*G41*(O41/100))/AB41,0) -> 0 | AH41: =IF(T41="Yes","Tier 0: Emergency",IF(AG41>=100,"Tier 1: Fast Track",IF(AG41>=50,"Tier 2: Standard Delivery",IF(AG41>=10,"Tier 3: Custom Engagement","Tier 4: Backlog")))) -> Tier 4: Backlog | AI41: =IF(T41="Yes","Negative (Risk of Loss)",IF(L41="Retention/Risk of Loss","Negative (Risk of Loss)",IF(AND(K41>0,OR(L41="New Contract",L41="Expansion")),"Positive (New Revenue)","Neutral (Internal/Platform)"))) -> Neutral (Internal/Platform) | AJ41: =IF(NOT(ISBLANK(K41)),K41*(O41/100),0) -> 0 | AP41: =COUNTIF(Master_Data_JIRA_Tickets!I:I,B41) -> 0 | AS41: No | AT41: Not Started | AU41: No
B42: F-040 | C42: Trade Processing - 100% Accuracy Validation | D42: Trade Processing | E42: Platform Improvements | F42: Q1 2026 | G42: 5 | H42: Multiple | I42: 0 | J42: Platform Enhancement | X42: =IF(H42="Multiple",IF(ISBLANK(I42),1,LEN(I42)-LEN(SUBSTITUTE(I42,",",""))+1),IF(NOT(ISBLANK(I42)),LEN(I42)-LEN(SUBSTITUTE(I42,",",""))+2,1)) -> 1 | Z42: =IF(NOT(ISBLANK(Y42)),Y42-TODAY(),"") | AG42: =IF(AND(NOT(ISBLANK(K42)),NOT(ISBLANK(G42)),NOT(ISBLANK(O42)),NOT(ISBLANK(AB42)),AB42>0),(K42*G42*(O42/100))/AB42,0) -> 0 | AH42: =IF(T42="Yes","Tier 0: Emergency",IF(AG42>=100,"Tier 1: Fast Track",IF(AG42>=50,"Tier 2: Standard Delivery",IF(AG42>=10,"Tier 3: Custom Engagement","Tier 4: Backlog")))) -> Tier 4: Backlog | AI42: =IF(T42="Yes","Negative (Risk of Loss)",IF(L42="Retention/Risk of Loss","Negative (Risk of Loss)",IF(AND(K42>0,OR(L42="New Contract",L42="Expansion")),"Positive (New Revenue)","Neutral (Internal/Platform)"))) -> Neutral (Internal/Platform) | AJ42: =IF(NOT(ISBLANK(K42)),K42*(O42/100),0) -> 0 | AP42: =COUNTIF(Master_Data_JIRA_Tickets!I:I,B42) -> 0 | AS42: No | AT42: Not Started | AU42: No
B43: F-041 | C43: Security Settlements - Break Resolution Automation | D43: Security Settlements | E43: Platform Improvements | F43: Q2 2026 | G43: 5 | H43: Multiple | I43: 0 | J43: Platform Enhancement | X43: =IF(H43="Multiple",IF(ISBLANK(I43),1,LEN(I43)-LEN(SUBSTITUTE(I43,",",""))+1),IF(NOT(ISBLANK(I43)),LEN(I43)-LEN(SUBSTITUTE(I43,",",""))+2,1)) -> 1 | Z43: =IF(NOT(ISBLANK(Y43)),Y43-TODAY(),"") | AG43: =IF(AND(NOT(ISBLANK(K43)),NOT(ISBLANK(G43)),NOT(ISBLANK(O43)),NOT(ISBLANK(AB43)),AB43>0),(K43*G43*(O43/100))/AB43,0) -> 0 | AH43: =IF(T43="Yes","Tier 0: Emergency",IF(AG43>=100,"Tier 1: Fast Track",IF(AG43>=50,"Tier 2: Standard Delivery",IF(AG43>=10,"Tier 3: Custom Engagement","Tier 4: Backlog")))) -> Tier 4: Backlog | AI43: =IF(T43="Yes","Negative (Risk of Loss)",IF(L43="Retention/Risk of Loss","Negative (Risk of Loss)",IF(AND(K43>0,OR(L43="New Contract",L43="Expansion")),"Positive (New Revenue)","Neutral (Internal/Platform)"))) -> Neutral (Internal/Platform) | AJ43: =IF(NOT(ISBLANK(K43)),K43*(O43/100),0) -> 0 | AP43: =COUNTIF(Master_Data_JIRA_Tickets!I:I,B43) -> 0 | AS43: No | AT43: Not Started | AU43: No
B44: F-042 | C44: SSI - Real-time Data Validation | D44: Standing Settlement Instructions | E44: Platform Improvements | F44: Q1 2026 | G44: 5 | H44: Multiple | I44: 0 | J44: Platform Enhancement | X44: =IF(H44="Multiple",IF(ISBLANK(I44),1,LEN(I44)-LEN(SUBSTITUTE(I44,",",""))+1),IF(NOT(ISBLANK(I44)),LEN(I44)-LEN(SUBSTITUTE(I44,",",""))+2,1)) -> 1 | Z44: =IF(NOT(ISBLANK(Y44)),Y44-TODAY(),"") | AG44: =IF(AND(NOT(ISBLANK(K44)),NOT(ISBLANK(G44)),NOT(ISBLANK(O44)),NOT(ISBLANK(AB44)),AB44>0),(K44*G44*(O44/100))/AB44,0) -> 0 | AH44: =IF(T44="Yes","Tier 0: Emergency",IF(AG44>=100,"Tier 1: Fast Track",IF(AG44>=50,"Tier 2: Standard Delivery",IF(AG44>=10,"Tier 3: Custom Engagement","Tier 4: Backlog")))) -> Tier 4: Backlog | AI44: =IF(T44="Yes","Negative (Risk of Loss)",IF(L44="Retention/Risk of Loss","Negative (Risk of Loss)",IF(AND(K44>0,OR(L44="New Contract",L44="Expansion")),"Positive (New Revenue)","Neutral (Internal/Platform)"))) -> Neutral (Internal/Platform) | AJ44: =IF(NOT(ISBLANK(K44)),K44*(O44/100),0) -> 0 | AP44: =COUNTIF(Master_Data_JIRA_Tickets!I:I,B44) -> 0 | AS44: No | AT44: Not Started | AU44: No
B45: F-043 | C45: Matching Engine - External Break Detection | D45: Matching Engine | E45: Platform Improvements | F45: Q2 2026 | G45: 4 | H45: Multiple | I45: 0 | J45: Platform Enhancement | X45: =IF(H45="Multiple",IF(ISBLANK(I45),1,LEN(I45)-LEN(SUBSTITUTE(I45,",",""))+1),IF(NOT(ISBLANK(I45)),LEN(I45)-LEN(SUBSTITUTE(I45,",",""))+2,1)) -> 1 | Z45: =IF(NOT(ISBLANK(Y45)),Y45-TODAY(),"") | AG45: =IF(AND(NOT(ISBLANK(K45)),NOT(ISBLANK(G45)),NOT(ISBLANK(O45)),NOT(ISBLANK(AB45)),AB45>0),(K45*G45*(O45/100))/AB45,0) -> 0 | AH45: =IF(T45="Yes","Tier 0: Emergency",IF(AG45>=100,"Tier 1: Fast Track",IF(AG45>=50,"Tier 2: Standard Delivery",IF(AG45>=10,"Tier 3: Custom Engagement","Tier 4: Backlog")))) -> Tier 4: Backlog | AI45: =IF(T45="Yes","Negative (Risk of Loss)",IF(L45="Retention/Risk of Loss","Negative (Risk of Loss)",IF(AND(K45>0,OR(L45="New Contract",L45="Expansion")),"Positive (New Revenue)","Neutral (Internal/Platform)"))) -> Neutral (Internal/Platform) | AJ45: =IF(NOT(ISBLANK(K45)),K45*(O45/100),0) -> 0 | AP45: =COUNTIF(Master_Data_JIRA_Tickets!I:I,B45) -> 0 | AS45: No | AT45: Not Started | AU45: No
B46: F-044 | C46: One View - Cross-System Integration | D46: One View | E46: Platform Improvements | F46: Q2 2026 | G46: 5 | H46: Multiple | I46: 0 | J46: Platform Enhancement | X46: =IF(H46="Multiple",IF(ISBLANK(I46),1,LEN(I46)-LEN(SUBSTITUTE(I46,",",""))+1),IF(NOT(ISBLANK(I46)),LEN(I46)-LEN(SUBSTITUTE(I46,",",""))+2,1)) -> 1 | Z46: =IF(NOT(ISBLANK(Y46)),Y46-TODAY(),"") | AG46: =IF(AND(NOT(ISBLANK(K46)),NOT(ISBLANK(G46)),NOT(ISBLANK(O46)),NOT(ISBLANK(AB46)),AB46>0),(K46*G46*(O46/100))/AB46,0) -> 0 | AH46: =IF(T46="Yes","Tier 0: Emergency",IF(AG46>=100,"Tier 1: Fast Track",IF(AG46>=50,"Tier 2: Standard Delivery",IF(AG46>=10,"Tier 3: Custom Engagement","Tier 4: Backlog")))) -> Tier 4: Backlog | AI46: =IF(T46="Yes","Negative (Risk of Loss)",IF(L46="Retention/Risk of Loss","Negative (Risk of Loss)",IF(AND(K46>0,OR(L46="New Contract",L46="Expansion")),"Positive (New Revenue)","Neutral (Internal/Platform)"))) -> Neutral (Internal/Platform) | AJ46: =IF(NOT(ISBLANK(K46)),K46*(O46/100),0) -> 0 | AP46: =COUNTIF(Master_Data_JIRA_Tickets!I:I,B46) -> 0 | AS46: No | AT46: Not Started | AU46: No
B47: F-045 | C47: Loan Operations - Application Automation | D47: Loan Operations | E47: Platform Improvements | F47: Q3 2026 | G47: 4 | H47: Multiple | I47: 0 | J47: Platform Enhancement | X47: =IF(H47="Multiple",IF(ISBLANK(I47),1,LEN(I47)-LEN(SUBSTITUTE(I47,",",""))+1),IF(NOT(ISBLANK(I47)),LEN(I47)-LEN(SUBSTITUTE(I47,",",""))+2,1)) -> 1 | Z47: =IF(NOT(ISBLANK(Y47)),Y47-TODAY(),"") | AG47: =IF(AND(NOT(ISBLANK(K47)),NOT(ISBLANK(G47)),NOT(ISBLANK(O47)),NOT(ISBLANK(AB47)),AB47>0),(K47*G47*(O47/100))/AB47,0) -> 0 | AH47: =IF(T47="Yes","Tier 0: Emergency",IF(AG47>=100,"Tier 1: Fast Track",IF(AG47>=50,"Tier 2: Standard Delivery",IF(AG47>=10,"Tier 3: Custom Engagement","Tier 4: Backlog")))) -> Tier 4: Backlog | AI47: =IF(T47="Yes","Negative (Risk of Loss)",IF(L47="Retention/Risk of Loss","Negative (Risk of Loss)",IF(AND(K47>0,OR(L47="New Contract",L47="Expansion")),"Positive (New Revenue)","Neutral (Internal/Platform)"))) -> Neutral (Internal/Platform) | AJ47: =IF(NOT(ISBLANK(K47)),K47*(O47/100),0) -> 0 | AP47: =COUNTIF(Master_Data_JIRA_Tickets!I:I,B47) -> 0 | AS47: No | AT47: Not Started | AU47: No
B48: F-046 | C48: Core Reconciliation - Multi-System Support | D48: Core Reconciliation | E48: Platform Improvements | F48: Q1 2026 | G48: 5 | H48: Multiple | I48: 0 | J48: Platform Enhancement | X48: =IF(H48="Multiple",IF(ISBLANK(I48),1,LEN(I48)-LEN(SUBSTITUTE(I48,",",""))+1),IF(NOT(ISBLANK(I48)),LEN(I48)-LEN(SUBSTITUTE(I48,",",""))+2,1)) -> 1 | Z48: =IF(NOT(ISBLANK(Y48)),Y48-TODAY(),"") | AG48: =IF(AND(NOT(ISBLANK(K48)),NOT(ISBLANK(G48)),NOT(ISBLANK(O48)),NOT(ISBLANK(AB48)),AB48>0),(K48*G48*(O48/100))/AB48,0) -> 0 | AH48: =IF(T48="Yes","Tier 0: Emergency",IF(AG48>=100,"Tier 1: Fast Track",IF(AG48>=50,"Tier 2: Standard Delivery",IF(AG48>=10,"Tier 3: Custom Engagement","Tier 4: Backlog")))) -> Tier 4: Backlog | AI48: =IF(T48="Yes","Negative (Risk of Loss)",IF(L48="Retention/Risk of Loss","Negative (Risk of Loss)",IF(AND(K48>0,OR(L48="New Contract",L48="Expansion")),"Positive (New Revenue)","Neutral (Internal/Platform)"))) -> Neutral (Internal/Platform) | AJ48: =IF(NOT(ISBLANK(K48)),K48*(O48/100),0) -> 0 | AP48: =COUNTIF(Master_Data_JIRA_Tickets!I:I,B48) -> 0 | AS48: No | AT48: Not Started | AU48: No
B49: F-047 | C49: DeepPilot - Financial Services Context Mining | D49: DeepPilot | E49: Platform Improvements | F49: Q2 2026 | G49: 5 | H49: Multiple | I49: 0 | J49: Platform Enhancement | X49: =IF(H49="Multiple",IF(ISBLANK(I49),1,LEN(I49)-LEN(SUBSTITUTE(I49,",",""))+1),IF(NOT(ISBLANK(I49)),LEN(I49)-LEN(SUBSTITUTE(I49,",",""))+2,1)) -> 1 | Z49: =IF(NOT(ISBLANK(Y49)),Y49-TODAY(),"") | AG49: =IF(AND(NOT(ISBLANK(K49)),NOT(ISBLANK(G49)),NOT(ISBLANK(O49)),NOT(ISBLANK(AB49)),AB49>0),(K49*G49*(O49/100))/AB49,0) -> 0 | AH49: =IF(T49="Yes","Tier 0: Emergency",IF(AG49>=100,"Tier 1: Fast Track",IF(AG49>=50,"Tier 2: Standard Delivery",IF(AG49>=10,"Tier 3: Custom Engagement","Tier 4: Backlog")))) -> Tier 4: Backlog | AI49: =IF(T49="Yes","Negative (Risk of Loss)",IF(L49="Retention/Risk of Loss","Negative (Risk of Loss)",IF(AND(K49>0,OR(L49="New Contract",L49="Expansion")),"Positive (New Revenue)","Neutral (Internal/Platform)"))) -> Neutral (Internal/Platform) | AJ49: =IF(NOT(ISBLANK(K49)),K49*(O49/100),0) -> 0 | AP49: =COUNTIF(Master_Data_JIRA_Tickets!I:I,B49) -> 0 | AS49: No | AT49: Not Started | AU49: No

Sheet Master_Data_JIRA_Tickets
A1: jira_ticket_id | B1: jira_ticket_title | C1: jira_status | D1: jira_category | E1: project_key | F1: client_name | G1: effort_tshirt_size | H1: story_points | I1: mapped_feature_id | J1: mapped_feature_name | K1: assigned_engineer | L1: sprint | M1: created_date | N1: target_date | O1: completed_date
A2: PR-1555 | B2: Enable Conditional Reconciliation | C2: New | D2: Product Roadmap | E2: PR | M2: 45973
A3: UI-694 | B3: UI and Dashboard Improvements to DeepRecon to Support Boradridge | C3: To Do | D3: Front End Development | E3: UI | M3: 45972
A4: BACK-1481 | B4: PDF Conversion fails for PNG files | C4: To Do | D4: Back End Development | E4: BACK | M4: 45972
A5: UI-693 | B5: Add a new blockly block to use equivalency lists on full strings | C5: To Do | D5: Front End Development | E5: UI | M5: 45972
A6: UI-692 | B6: Allow filtering and sorting by custom fields in Actionable data | C6: To Do | D6: Front End Development | E6: UI | M6: 45972
A7: UI-691 | B7: Display Custom fields in Actionable Data | C7: To Do | D7: Front End Development | E7: UI | M7: 45972
A8: UI-690 | B8: Allow the user to create custom fields when configuring Automations | C8: To Do | D8: Front End Development | E8: UI | M8: 45972
A9: UI-689 | B9: Implement Custom fields (key-value pairs) for Deep Recon | C9: To Do | D9: Front End Development | E9: UI | M9: 45972
A10: UI-688 | B10: Deploy the latest UI image to FIS Tenant | C10: To Do | D10: Front End Development | E10: UI | M10: 45972
A11: UI-687 | B11: UI - Configure FIS Tenant | C11: To Do | D11: Front End Development | E11: UI | M11: 45972
A12: CI-894 | B12: Create Tenant for FIS - US region | C12: To Do | D12: Core-Infrastructure | E12: CI | M12: 45972
A13: CI-893 | B13: Infra - Configure Tenant for FIS | C13: To Do | D13: Core-Infrastructure | E13: CI | M13: 45972
A14: BACK-1480 | B14: Integrate CrowdStrike security scanning into CI/CD pipeline for Extraction service | C14: In Progress | D14: Back End Development | E14: BACK | K14: Kalvin Willison | M14: 45972
A15: PR-1553 | B15: Set Up/Configure FIS Tenant | C15: Planning | D15: Product Roadmap | E15: PR | M15: 45972
A16: CI-892 | B16: Create Tenant for BBVA - EU region | C16: To Do | D16: Core-Infrastructure | E16: CI | M16: 45971
A17: CI-891 | B17: Infra - Configure Tenant for BBVA | C17: To Do | D17: Core-Infrastructure | E17: CI | M17: 45971
A18: UI-686 | B18: Deploy the latest UI image to BBVA Tenant | C18: To Do | D18: Front End Development | E18: UI | M18: 45971
A19: UI-685 | B19: Configure BBVA Tenant | C19: To Do | D19: Front End Development | E19: UI | M19: 45971
A20: CI-890 | B20: Create Tenant for CTC for EU region | C20: To Do | D20: Core-Infrastructure | E20: CI | M20: 45971
A21: CI-889 | B21: Infra - Configure Tenant for CTC | C21: To Do | D21: Core-Infrastructure | E21: CI | M21: 45971
A22: UI-684 | B22: Deploy the latest UI image to CTC Tenant | C22: To Do | D22: Front End Development | E22: UI | M22: 45971
A23: UI-683 | B23: UI - Configure CTC Tenant | C23: To Do | D23: Front End Development | E23: UI | M23: 45971
A24: PR-1552 | B24: Set Up/Configure BBVA Tenant | C24: Planning | D24: Product Roadmap | E24: PR | M24: 45971
A25: PR-1551 | B25: Set Up/Configure CTC Tenant | C25: Planning | D25: Product Roadmap | E25: PR | M25: 45971
A26: SC-299 | B26: Priority: Address Wiz-Identified Assets (13 Assets, 390 C+H) | C26: To Do | D26: Security & Compliance | E26: SC | M26: 45967
A27: UI-682 | B27: Enhance "Golden Source" Picker for Colony Bank | C27: In Progress | D27: Front End Development | E27: UI | H27: 2 | K27: Owen Riley | M27: 45966
A28: UI-681 | B28: Allow for Document Orientation Adjustment | C28: To Do | D28: Front End Development | E28: UI | M28: 45966
A29: BACK-1477 | B29: Configure the API key for the news sources | C29: To Do | D29: Back End Development | E29: BACK | M29: 45966
A30: CI-887 | B30: Helm chart changes for new k8s job | C30: To Do | D30: Core-Infrastructure | E30: CI | M30: 45966
A31: CI-886 | B31: Update Terraform for the new k8s job | C31: To Do | D31: Core-Infrastructure | E31: CI | M31: 45966
A32: BACK-1474 | B32: Create a scheduled data fetch k8s job | C32: To Do | D32: Back End Development | E32: BACK | M32: 45966
A33: BACK-1472 | B33: Add user defined key-value pairs that can be associated with a message | C33: To Do | D33: Back End Development | E33: BACK | H33: 5 | M33: 45965
A34: BACK-1471 | B34: Add Custom Fields in Deep Recon | C34: To Do | D34: Back End Development | E34: BACK | M34: 45965
A35: BACK-1470 | B35: Update the prediction API to include custom fields | C35: To Do | D35: Back End Development | E35: BACK | H35: 3 | M35: 45965
A36: BACK-1469 | B36: Allow Automation to use custom fields | C36: To Do | D36: Back End Development | E36: BACK | H36: 6 | M36: 45965
A37: BACK-1468 | B37: Use equivalency lists on full strings | C37: To Do | D37: Back End Development | E37: BACK | H37: 3 | M37: 45965
A38: BACK-1467 | B38: Create a custom FEEL function that would use equivalency lists and a string | C38: Canceled | D38: Back End Development | E38: BACK | M38: 45965
A39: BACK-1466 | B39: FEEL / Equivalency matching improvements to build Automations for Accenture | C39: To Do | D39: Back End Development | E39: BACK | M39: 45965
A40: UI-678 | B40: Create Absolute Value Puzzle Piece | C40: Code Review | D40: Front End Development | E40: UI | H40: 2 | K40: Owen Riley | M40: 45965
A41: BACK-1465 | B41: Deep Pilot - Light Extraction - Some Excel Files with multiple tables merge the tables and do not extract any aliases | C41: To Do | D41: Back End Development | E41: BACK | M41: 45965
A42: BACK-1464 | B42: Deep Pilot - Hardcode some checklist items to be sent to Allegro without review (Colonybank) | C42: In Progress | D42: Back End Development | E42: BACK | K42: Kannal Mutharasu | M42: 45965
A43: BACK-1463 | B43: Additional Allegro Field Mapping | C43: Blocked | D43: Back End Development | E43: BACK | K43: Kannal Mutharasu | M43: 45965
A44: CI-885 | B44: Update kserve inference service resources | C44: In Testing | D44: Core-Infrastructure | E44: CI | K44: Chad Hegerhorst | M44: 45965
A45: BACK-1462 | B45: Deep Recon - Detach Automations from Outlook (for Accenture) | C45: To Do | D45: Back End Development | E45: BACK | H45: 5 | M45: 45964
A46: BACK-1436 | B46: Deep Recon - Always run on import Automations (Broadridge) | C46: To Do | D46: Back End Development | E46: BACK | H46: 5 | M46: 45961
A47: SC-298 | B47: Fix Remaining Application-Level Dependencies | C47: To Do | D47: Security & Compliance | E47: SC | M47: 45961
A48: SC-297 | B48: Standardize Alpine-based Images to 3.22 | C48: To Do | D48: Security & Compliance | E48: SC | M48: 45961
A49: SC-296 | B49: Standardize Ubuntu-based Images to 24.04 LTS | C49: To Do | D49: Security & Compliance | E49: SC | M49: 45961
A50: SC-295 | B50: [HIGH] GHSA-9763-4f94-gfch: github.com/cloudflare/circl vulnerability in 1 images | C50: To Do | D50: Security & Compliance | E50: SC | M50: 45960
A51: SC-294 | B51: [HIGH] GHSA-7jwh-3vrq-q3m8: github.com/jackc/pgproto3/v2 vulnerability in 1 images | C51: To Do | D51: Security & Compliance | E51: SC | M51: 45960
A52: SC-293 | B52: [HIGH] CVE-2025-8194: python vulnerability in 1 images (Cross-Category) | C52: To Do | D52: Security & Compliance | E52: SC | M52: 45960
A53: SC-292 | B53: [HIGH] CVE-2025-7425: libxml2 vulnerability in 1 images (Cross-Category) | C53: To Do | D53: Security & Compliance | E53: SC | M53: 45960
A54: SC-291 | B54: [HIGH] CVE-2025-7424: libxslt1.1 vulnerability in 1 images | C54: To Do | D54: Security & Compliance | E54: SC | M54: 45960
A55: SC-290 | B55: [HIGH] CVE-2025-62727: starlette vulnerability in 1 images | C55: To Do | D55: Security & Compliance | E55: SC | M55: 45960
A56: SC-289 | B56: [HIGH] CVE-2025-62157: github.com/argoproj/argo-workflows/v3 vulnerability in 1 images | C56: To Do | D56: Security & Compliance | E56: SC | M56: 45960
A57: SC-288 | B57: [HIGH] CVE-2025-62156: github.com/argoproj/argo-workflows/v3 vulnerability in 1 images | C57: To Do | D57: Security & Compliance | E57: SC | M57: 45960
A58: SC-287 | B58: [HIGH] CVE-2025-6021: libxml2 vulnerability in 1 images (Cross-Category) | C58: To Do | D58: Security & Compliance | E58: SC | M58: 45960
... A275: SC-70 | B275: [CRITICAL] CVE-2019-8457: libdb5.3 vulnerability in 1 images | C275: To Do | D275: Security & Compliance | E275: SC | M275: 45960
A276: BACK-1434 | B276: Add Indexes for Selects Executed from Preprocessor | C276: Canceled | D276: Back End Development | E276: BACK | K276: Lane Terry | M276: 45960
A277: BACK-1431 | B277: Unknown Content Transfer Encoding for Email | C277: To Do | D277: Back End Development | E277: BACK | M277: 45958
A278: BACK-1430 | B278: ArrayIndexOutOfBounds Processing Actors | C278: In Progress | D278: Back End Development | E278: BACK | K278: Lane Terry | M278: 45958
A279: BACK-1427 | B279: Add LLM support to the intent agent | C279: To Do | D279: Back End Development | E279: BACK | H279: 8 | M279: 45958
A280: BACK-1425 | B280: Deep Pilot - Testing Suite - Add the actualPassCount and actualFailCount to the endpoint | C280: To Do | D280: Back End Development | E280: BACK | K280: Kannal Mutharasu | M280: 45957
A281: BACK-1422 | B281: DTCC FEEL expression timing out | C281: Canceled | D281: Back End Development | E281: BACK | K281: Treven Trujillo | M281: 45957
A282: SC-69 | B282: Application Vulnerabilities | C282: To Do | D282: Security & Compliance | E282: SC | M282: 45954
A283: SC-68 | B283: Infrastructure Vulnerabilities | C283: To Do | D283: Security & Compliance | E283: SC | M283: 45954
A284: BACK-1417 | B284: Prediction records in broken state | C284: To Do | D284: Back End Development | E284: BACK | M284: 45952
A285: BACK-1416 | B285: Make JPM dealfeed lambda more resilient | C285: To Do | D285: Back End Development | E285: BACK | M285: 45951
A286: FB-2406 | B286: Prepare to process new data | C286: In Progress | D286: FILBERT | E286: FB | K286: Anna Kamionowska | M286: 45951
A287: FB-2405 | B287: Create a risk metric for advisor attrition model | C287: To Do | D287: FILBERT | E287: FB | K287: Anna Kamionowska | M287: 45951
A288: BACK-1414 | B288: Tune DeepGPT Prompts for Generic Use Cases | C288: To Do | D288: Back End Development | E288: BACK | M288: 45950
A289: BACK-1412 | B289: Trigger Automated Annotations on Content Map Upload | C289: To Do | D289: Back End Development | E289: BACK | M289: 45950
A290: BACK-1411 | B290: Add Automated Annotation Configuration to Content Maps API | C290: To Do | D290: Back End Development | E290: BACK | M290: 45950
A291: BACK-1410 | B291: Broadridge - Automation triggered on the emails with non-matching criteria | C291: To Do | D291: Back End Development | E291: BACK | M291: 45947
A292: BACK-1405 | B292: Intent Agent - Regex causes Intent Agent to freeze when processing a large attachment | C292: To Do | D292: Back End Development | E292: BACK | M292: 45945
A293: UI-668 | B293: Deep Pilot - Show extraction progress once the source has been updated | C293: In Progress | D293: Front End Development | E293: UI | H293: 2 | K293: Owen Riley | M293: 45944
A294: BACK-1402 | B294: Deep Pilot - Re-enable .zip reprocessing | C294: To Do | D294: Back End Development | E294: BACK | M294: 45944
A295: BACK-1401 | B295: Large Check Ingestion - Colony | C295: To Do | D295: Back End Development | E295: BACK | H295: 5 | M295: 45944
A296: UI-666 | B296: Content Maps - 2 tables in Excel are merged into a single table | C296: To Do | D296: Front End Development | E296: UI | M296: 45940
A297: BACK-1400 | B297: Email Replies not loading message details | C297: To Do | D297: Back End Development | E297: BACK | M297: 45940
A298: BACK-1399 | B298: 30-50 minute delay between email received and created in DeepSee | C298: To Do | D298: Back End Development | E298: BACK | M298: 45940
A299: BACK-1398 | B299: Deep Pilot - Content Maps updated through "Configure Sources" are set to Archived | C299: To Do | D299: Back End Development | E299: BACK | M299: 45940
A300: BACK-1393 | B300: DeepRecon Email Ingestion | C300: To Do | D300: Back End Development | E300: BACK | G300: Large | M300: 45939
A301: BACK-1392 | B301: Update Outlook in Batches Downstream From DeepRecon | C301: To Do | D301: Back End Development | E301: BACK | M301: 45939
A302: BACK-1391 | B302: If a term in a reconciliation is not in a subgroup it can mess up the subgroup matching for that source | C302: To Do | D302: Back End Development | E302: BACK | M302: 45939
A303: BACK-1390 | B303: Pull Message Updates From Monitored Folders Using Delta Query | C303: To Do | D303: Back End Development | E303: BACK | M303: 45939
A304: BACK-1389 | B304: Pull Created Emails Only From Inbox Using Delta Query | C304: To Do | D304: Back End Development | E304: BACK | M304: 45939
A305: BACK-1388 | B305: Track Monitored Folders for Customer Mailboxes | C305: To Do | D305: Back End Development | E305: BACK | M305: 45939
A306: BACK-1387 | B306: Apache HttpComponents Client Configuration for DeepPilot | C306: To Do | D306: Back End Development | E306: BACK | M306: 45939
A307: BACK-1382 | B307: Export for Vantage Commercial Lending Work Items | C307: In Progress | D307: Back End Development | E307: BACK | H307: 3 | K307: Darius Ouderkirk | M307: 45939
A308: BACK-1381 | B308: Update Annotations to Match Term Group Updates | C308: Canceled | D308: Back End Development | E308: BACK | M308: 45939
A309: BACK-1380 | B309: Intent Agent - Excel tabs are not split when using Sync to DeepSee from Salesforce | C309: To Do | D309: Back End Development | E309: BACK | M309: 45938
A310: BACK-1378 | B310: Email couldn't be processed | C310: Canceled | D310: Back End Development | E310: BACK | K310: Aleksander Winski | M310: 45938
A311: CI-876 | B311: Ability to schedule model training | C311: To Do | D311: Core-Infrastructure | E311: CI | M311: 45937
A312: CI-874 | B312: Automatically Deploy latest modelchain when training is done | C312: To Do | D312: Core-Infrastructure | E312: CI | M312: 45937
A313: BACK-1375 | B313: Success/Failure Handler | C313: To Do | D313: Back End Development | E313: BACK | M313: 45937
A314: BACK-1374 | B314: OpenJDK 21 Container Image | C314: To Do | D314: Back End Development | E314: BACK | H314: 3 | M314: 45937
A315: BACK-1372 | B315: CI-CD for DeepRecon Platform | C315: To Do | D315: Back End Development | E315: BACK | M315: 45937
A316: CI-871 | B316: Update training workflow to not use same name for training dataset | C316: To Do | D316: Core-Infrastructure | E316: CI | K316: Chad Hegerhorst | M316: 45933
...

Sheet Master_Data_Sales_Pipeline
B2: Opportunity_ID | C2: Opportunity_Name | D2: Account_Name | E2: Stage | F2: ARR_Value | G2: Close_Date | H2: Probability_% | I2: Owner | J2: Agent_Type | K2: Mapped_Feature_ID | L2: Status | M2: Created_Date | N2: Last_Activity_Date | O2: Notes | P2: Weighted_ARR | Q2: Days_in_Stage
B3: OPP-001 | C3: DTCC Trade Processing POC to Production | D3: DTCC | E3: Closed Won | F3: 750000 | G3: 2025-12-31 | H3: 1 | I3: Steve Shillingford | J3: Trade Processing | K3: F-026 | L3: Active | M3: 2025-06-15 | N3: 2025-10-31 | P3: =F3*(H3/100) -> 7500 | Q3: =IF(NOT(ISBLANK(N3)),TODAY()-N3,"") -> 8
B4: OPP-002 | C4: Broadridge Email Automation Expansion | D4: Broadridge | E4: Closed Won | F4: 500000 | G4: 2025-11-30 | H4: 1 | I4: Steve Shillingford | J4: Email Automation | K4: F-030 | L4: Active | M4: 2025-07-01 | N4: 2025-10-15 | P4: =F4*(H4/100) -> 5000 | Q4: =IF(NOT(ISBLANK(N4)),TODAY()-N4,"") -> 24
B5: OPP-003 | C5: Colony Bank SSI Deployment | D5: Regional Banks - Colony Bank | E5: Closed Won | F5: 200000 | G5: 2025-12-15 | H5: 1 | I5: Armen Sargysan | J5: Standing Settlement Instructions | K5: F-036 | L5: Active | M5: 2025-08-01 | N5: 2025-11-01 | P5: =F5*(H5/100) -> 2000 | Q5: =IF(NOT(ISBLANK(N5)),TODAY()-N5,"") -> 7
B6: OPP-004 | C6: Accenture Multi-Agent Platform | D6: Accenture | E6: Closed Won | F6: 1200000 | G6: 2025-10-31 | H6: 1 | I6: Steve Shillingford | J6: Platform (All Agents) | K6: F-034, F-035 | L6: Active | M6: 2025-05-01 | N6: 2025-10-25 | P6: =F6*(H6/100) -> 12000 | Q6: =IF(NOT(ISBLANK(N6)),TODAY()-N6,"") -> 14
B7: OPP-005 | C7: JP Morgan Reconciliation Annual Renewal | D7: JP Morgan | E7: Closed Won | F7: 3000000 | G7: 2025-12-31 | H7: 1 | I7: Steve Shillingford | J7: Core Reconciliation | K7: F-032 | L7: Renewal | M7: 2024-12-01 | N7: 2025-11-05 | P7: =F7*(H7/100) -> 30000 | Q7: =IF(NOT(ISBLANK(N7)),TODAY()-N7,"") -> 3
B8: OPP-006 | C8: Sunwest Bank SSI Deployment | D8: Regional Banks - Sunwest Bank | E8: Contract Negotiation | F8: 180000 | G8: 2026-01-31 | H8: 0.8 | I8: Armen Sargysan | J8: Standing Settlement Instructions | K8: F-037 | L8: Active | M8: 2025-09-01 | N8: 2025-11-05 | P8: =F8*(H8/100) -> 1440 | Q8: =IF(NOT(ISBLANK(N8)),TODAY()-N8,"") -> 3
B9: OPP-007 | C9: Large Bank Trade Processing Platform | D9: [Confidential - Large US Bank] | E9: Contract Negotiation | F9: 2500000 | G9: 2026-02-28 | H9: 0.8 | I9: Steve Shillingford | J9: Trade Processing | K9: F-040 | L9: Active | M9: 2025-07-15 | N9: 2025-11-06 | P9: =F9*(H9/100) -> 20000 | Q9: =IF(NOT(ISBLANK(N9)),TODAY()-N9,"") -> 2
B10: OPP-008 | C10: Vantage Bank Custom Reconciliation POC | D10: Regional Banks - Vantage Bank | E10: POC | F10: 200000 | G10: 2026-03-31 | H10: 0.5 | I10: Armen Sargysan | J10: Core Reconciliation | K10: F-038 | L10: At Risk | M10: 2025-08-15 | N10: 2025-10-30 | O10: Client tired of waiting, requires prepayment or binding contract | P10: =F10*(H10/100) -> 1000 | Q10: =IF(NOT(ISBLANK(N10)),TODAY()-N10,"") -> 9
B11: OPP-009 | C11: Insurance Company Loan Operations | D11: [Prospect - Insurance Co A] | E11: POC | F11: 600000 | G11: 2026-04-30 | H11: 0.6 | I11: Armen Sargysan | J11: Loan Operations | K11: F-045 | L11: Active | M11: 2025-09-01 | N11: 2025-11-04 | P11: =F11*(H11/100) -> 3600 | Q11: =IF(NOT(ISBLANK(N11)),TODAY()-N11,"") -> 4
B12: OPP-010 | C12: Asset Manager Email Automation | D12: [Prospect - Asset Manager B] | E12: POC | F12: 400000 | G12: 2026-03-31 | H12: 0.6 | I12: Armen Sargysan | J12: Email Automation | K12: F-039 | L12: Active | M12: 2025-09-15 | N12: 2025-11-03 | P12: =F12*(H12/100) -> 2400 | Q12: =IF(NOT(ISBLANK(N12)),TODAY()-N12,"") -> 5
B13: OPP-011 | C13: Regional Bank Consortium Platform | D13: [Prospect - Regional Bank Consortium] | E13: Proposal | F13: 800000 | G13: 2026-05-31 | H13: 0.5 | I13: Steve Shillingford | J13: Platform (All Agents) | K13: Multiple platform features | L13: Active | M13: 2025-09-01 | N13: 2025-10-28 | P13: =F13*(H13/100) -> 4000 | Q13: =IF(NOT(ISBLANK(N13)),TODAY()-N13,"") -> 11
B14: OPP-012 | C14: Hedge Fund Trade Matching | D14: [Prospect - Hedge Fund D] | E14: Proposal | F14: 350000 | G14: 2026-04-30 | H14: 0.5 | I14: Armen Sargysan | J14: Matching Engine | K14: F-043 | L14: Active | M14: 2025-10-01 | N14: 2025-11-01 | P14: =F14*(H14/100) -> 1750 | Q14: =IF(NOT(ISBLANK(N14)),TODAY()-N14,"") -> 7
B15: OPP-013 | C15: Global Bank Security Settlements | D15: [Prospect - Global Bank E] | E15: Qualification | F15: 1500000 | G15: 2026-06-30 | H15: 0.3 | I15: Steve Shillingford | J15: Security Settlements | K15: F-041 | L15: Active | M15: 2025-10-01 | N15: 2025-11-02 | P15: =F15*(H15/100) -> 4500 | Q15: =IF(NOT(ISBLANK(N15)),TODAY()-N15,"") -> 6
B16: OPP-014 | C16: Investment Bank One View Platform | D16: [Prospect - Investment Bank F] | E16: Qualification | F16: 900000 | G16: 2026-07-31 | H16: 0.3 | I16: Armen Sargysan | J16: One View | K16: F-044 | L16: Active | M16: 2025-10-15 | N16: 2025-10-31 | P16: =F16*(H16/100) -> 2700 | Q16: =IF(NOT(ISBLANK(N16)),TODAY()-N16,"") -> 8
B17: OPP-015 | C17: European Bank Multi-Agent Exploration | D17: [Prospect - European Bank G] | E17: Introduction | F17: 2000000 | G17: 2026-09-30 | H17: 0.1 | I17: Steve Shillingford | J17: Platform (All Agents) | K17: Multiple platform features | L17: Early Stage | M17: 2025-10-20 | N17: 2025-10-25 | P17: =F17*(H17/100) -> 2000 | Q17: =IF(NOT(ISBLANK(N17)),TODAY()-N17,"") -> 14
B18: OPP-016 | C18: Pension Fund DeepPilot Discussion | D18: [Prospect - Pension Fund H] | E18: Introduction | F18: 500000 | G18: 2026-08-31 | H18: 0.1 | I18: Armen Sargysan | J18: DeepPilot | K18: F-047 | L18: Early Stage | M18: 2025-10-25 | N18: 2025-10-28 | P18: =F18*(H18/100) -> 500 | Q18: =IF(NOT(ISBLANK(N18)),TODAY()-N18,"") -> 11

Sheet Lookup_Tables
B2: Clients | D2: Agent_Types | F2: Pipeline_Stages | H2: Priority_Tiers | J2: Categories | L2: Team_Assignment | N2: Status_Options | P2: Revenue_Types | R2: Contract_Status | T2: Yes_No_Options | V2: PRD_Status_Options
B3: Broadridge | D3: Email Automation | F3: Introduction | H3: Tier 0: Emergency | J3: Core Infrastructure | L3: Frontend | N3: Not Started | P3: New Contract | R3: Signed | T3: Yes | V3: Complete
B4: DTCC | D4: Trade Processing | F4: Qualification | H4: Tier 1: Fast Track | J4: Client-Specific Work | L4: Backend | N4: In Progress | P4: Expansion | R4: Verbal Commitment | T4: No | V4: In Progress
B5: JP Morgan | D5: Security Settlements | F5: Proposal | H5: Tier 2: Standard Delivery | J5: Platform Improvements | L5: DevOps | N5: Blocked | P5: Retention/Risk of Loss | R5: POC | V5: Not Started
B6: Accenture | D6: Standing Settlement Instructions | F6: POC | H6: Tier 3: Custom Engagement | J6: API Development | L6: ML (Machine Learning) | N6: Completed | P6: Internal | R6: Exploratory | V6: N/A
B7: Regional Banks | D7: Matching Engine | F7: Contract Negotiation | H7: Tier 4: Backlog | J7: Bug Fixes | L7: Multiple Teams | N7: Cancelled
B8: Multiple | D8: One View | F8: Closed Won
B9: Internal | D9: Loan Operations | F9: Closed Lost
D10: Core Reconciliation
D11: DeepPilot
D12: Platform (All Agents)
D13: Platform (Analytics)

Sheet Master_Data_Client_Projects
B2: Project_ID | C2: Client_Name | D2: Project_Name | E2: Status | F2: Start_Date | G2: End_Date | H2: Project_Value | I2: Features_Required | J2: Mapped_Feature_IDs
B3: PROJ-001 | C3: DTCC | D3: DTCC Phase 1 Onboarding | E3: In Progress | F3: 2025-10-01 | G3: 2025-12-31 | H3: 750000 | I3: Trade Processing Agent, Core Reconciliation | J3: F-026, F-028
B4: PROJ-002 | C4: Broadridge | D4: Broadridge Email Automation Expansion | E4: In Progress | F4: 2025-09-01 | G4: 2025-11-30 | H4: 500000 | I4: Email Automation, Trade Processing Enhancement | J4: F-030, F-029
B5: PROJ-003 | C5: Regional Banks | D5: Colony Bank SSI Deployment | E5: In Progress | F5: 2025-11-01 | G5: 2025-12-15 | H5: 200000 | I5: SSI Agent | J5: F-036
B6: PROJ-004 | C6: Accenture | D6: Accenture Multi-Agent Platform | E6: In Progress | F6: 2025-08-01 | G6: 2026-02-28 | H6: 1200000 | I6: Multi-agent orchestration, Email Automation | J6: F-034, F-035
B7: PROJ-005 | C7: JP Morgan | D7: JP Morgan Annual Contract | E7: Active | F7: 2024-01-01 | G7: 2025-12-31 | H7: 3000000 | I7: Core Reconciliation, Security Settlements | J7: F-032, F-033

Sheet Master_Data_Won_Deals
B2: Client_Name | C2: Original_Contract_Value | D2: Renewal_Date | E2: Upsell_Opportunity | F2: Potential_Expansion_ARR | G2: Risk_Level
B3: DTCC | C3: 750000 | D3: 2026-12-31 | E3: Additional agents (Security Settlements, SSI) | F3: 400000 | G3: Low
B4: Broadridge | C4: 500000 | D4: 2026-11-30 | E4: Trade Processing + Email Automation expansion | F4: 300000 | G4: Medium (recent bug fix required)
B5: JP Morgan | C5: 3000000 | D5: 2026-12-31 | E5: Platform expansion, additional asset classes | F5: 500000 | G5: Low
B6: Accenture | C6: 1200000 | D6: 2026-10-31 | E6: New use cases, additional agents | F6: 800000 | G6: Low
B7: Colony Bank | C7: 200000 | D7: 2026-12-15 | E7: Additional regional banks | F7: 180000 | G7: Low

Sheet Scoring_Rubric
B2: DEEP SEE AI - SCORING RUBRIC & FORMULAS
B4: PRIORITY SCORE FORMULA:
B5: Priority_Score = (ARR_Amount × Replicability_Score × Conversion_Probability_%) / Effort_Estimate_Weeks
B7: Example Calculation:
B8: • ARR: $200,000
B9: • Replicability: 5 (all clients benefit)
B10: • Conversion Probability: 100%
B11: • Effort: 6 weeks
B12: • Priority_Score = (200,000 × 5 × 100%) / 6 = 166,667 → Tier 1: Fast Track
B14: TIER ASSIGNMENT LOGIC:
B15: Tier | C15: Criteria | D15: Description
B16: Tier 0: Emergency | C16: Revenue_at_Risk = 'Yes' | D16: Negative Revenue (client threatening to leave)
B17: Tier 1: Fast Track | C17: Priority_Score >= 100 | D17: High-value, replicable, high-probability
B18: Tier 2: Standard Delivery | C18: Priority_Score 50-99 | D18: Medium priority work
B19: Tier 3: Custom Engagement | C19: Priority_Score 10-49 | D19: Lower priority, often custom
B20: Tier 4: Backlog | C20: Priority_Score < 10 | D20: Low priority or exploratory
B22: CONVERSION PROBABILITY MAPPING:
B23: Pipeline Stage | C23: Probability
B24: Introduction | C24: 10%
B25: Qualification | C25: 30%
B26: Proposal | C26: 50%
B27: POC | C27: 60%
B28: Contract Negotiation | C28: 80%
B29: Closed Won | C29: 100%
B30: Closed Lost | C30: 0%
B32: REPLICABILITY SCORE (1-5):
B33: Score | C33: Definition
B34: 1 | C34: One-off custom build (single client only)
B35: 2 | C35: Somewhat custom (minimal reuse potential)
B36: 3 | C36: Approximately half of clients benefit
B37: 4 | C37: Most clients benefit
B38: 5 | C38: All clients benefit (platform enhancement)
B40: EFFORT T-SHIRT SIZING:
B41: Size | C41: Weeks
B42: S (Small) | C42: 2 weeks
B43: M (Medium) | C43: 4 weeks
B44: L (Large) | C44: 8 weeks
B45: XL (Extra Large) | C45: 12+ weeks
B47: EMERGENCY BUFFER RULE:
B48: • Each sprint: 80% committed work (Tier 1-2), 20% emergency buffer (Tier 0)
B49: • If Tier 0 items exceed 20% buffer → Escalate to Ryan for sprint re-prioritization

Sheet README_Instructions
B2: DEEP SEE AI UNIFIED PRIORITIZATION SYSTEM - INSTRUCTIONS
B4: FOR STEVE (Sales/CEO):
B5: Your role: Validate revenue and conversion data
B6: Steps:
B7: 1. Go to Tab: Master_Data_Features
B8: 2. Review columns: ARR_Amount, Revenue_Type, Contract_Status, Revenue_at_Risk, Conversion_Probability_%
B9: 3. To override Priority_Score: Enter your score in Manual_Override_Score column
B10: 4. Add context in Management_Notes column
B11: 5. View your dashboard: PIVOT - Management View
B12: Time Required: ~2 hours initial setup, <30 min weekly maintenance
B14: FOR RYAN (Product):
B15: Your role: Validate product features and replicability
... B49: TABS GUIDE:
B50: Tab Name | C50: Purpose
B51: Master_Data_Features | C51: 47 product features with prioritization
B52: Master_Data_JIRA_Tickets | C52: 198 engineering tickets mapped to features
B53: Master_Data_Sales_Pipeline | C53: 16 sales opportunities
B54: Master_Data_Client_Projects | C54: 5 active client projects
B55: Master_Data_Won_Deals | C55: 5 won deals & renewal tracking
B56: Lookup_Tables | C56: Reference data for dropdowns
B57: Scoring_Rubric | C57: Formula documentation
B58: README_Instructions | C58: This tab - user guide
B60: ARTEMIS STRATEGIC TRACKING (NEW):
B61: Ryan (Product) - Use these columns to track strategic platform work:
B62: • Artemis_Focus: Mark 'Yes' for strategic platform rebuild features
B63: • PRD_Status: Track PRD completion (Complete, In Progress, Not Started, N/A)
B64: • Epic_in_JIRA: Mark 'Yes' when epic is logged in JIRA
B65: 0
B66: View Strategic Balance:
B67: • Executive Dashboard - Shows Artemis vs Operational split
B68: • PIVOT_Strategic_vs_Operational - Detailed analysis by tier and PRD status
B69: 0
B70: Key Insight: Balance immediate revenue ($2.5M operational) vs platform scaling (Artemis)

Sheet Change_Log
B2: Date | C2: User | D2: Feature_ID | E2: Field_Changed | F2: Old_Value | G2: New_Value | H2: Reason_for_Change
B3: 2025-11-08 | C3: Steve Shillingford | D3: F-038 | E3: Conversion_Probability_% | F3: 60% | G3: 30% | H3: Vantage Bank losing interest, lowering conversion estimate

Sheet Executive_Dashboard
B2: EXECUTIVE SUMMARY DASHBOARD
B4: KEY PERFORMANCE INDICATORS
D6: Total ARR in Pipeline | F6: Total ARR at Risk | H6: Total Features | J6: Features Completed Q4
D7: =SUMIF(Master_Data_Features!K:K,">0",Master_Data_Features!K:K) -> 3030000 | F7: =_xlfn.SUMIFS(Master_Data_Features!K:K,Master_Data_Features!T:T,"Yes") -> -500000 | H7: =COUNTA(Master_Data_Features!B3:B49) -> 47 | J7: =_xlfn.COUNTIFS(Master_Data_Features!P:P,"Completed",Master_Data_Features!F:F,"Q4 2025") -> 0
D10: Average Priority Score | F10: On-Time Delivery Rate | H10: Pipeline Conversion Rate | J10: Eng Capacity Req (Q4)
D11: =AVERAGE(Master_Data_Features!AG3:AG49) -> 165.60284 | F11: =0 -> 0 | H11: =COUNTIF(Master_Data_Sales_Pipeline!E:E,"Closed Won")/COUNTA(Master_Data_Sales_Pipeline!B3:B18) -> 0.3125 | J11: =_xlfn.SUMIFS(Master_Data_Features!AB:AB,Master_Data_Features!F:F,"Q4 2025") -> 35
B14: TOP 5 LISTS
B16: Top 5 Highest Priority Features: | G16: Top 5 Clients by ARR:
B17: Feature ID | C17: Feature Name | D17: Priority Score | E17: ARR | G17: Client | H17: Total ARR
B18: Use Master_Data_Features sheet, sort by Priority_Score descending | G18: JP Morgan | H18: 3000000
G19: Accenture | H19: 1200000
G20: DTCC | H20: 750000
G21: Broadridge | H21: 500000
G22: Colony Bank | H22: 200000
B24: PIPELINE SUMMARY
B26: Stage | C26: Count | D26: Total ARR
B27: Closed Won Deals | C27: 5 | D27: $5.65M
B28: Contract Negotiation | C28: 2 | D28: $2.68M
B29: POC Stage | C29: 3 | D29: $1.20M
B30: Proposal Stage | C30: 2 | D30: $1.15M
B31: Qualification Stage | C31: 2 | D31: $2.40M
B32: Introduction Stage | C32: 2 | D32: $2.50M
B33: Total Active Pipeline | C33: 11 | D33: $9.93M
B35: STRATEGIC vs OPERATIONAL BALANCE
B37: Artemis Platform Work | C37: =COUNTIF(Master_Data_Features!AS:AS,"Yes") -> 7 | D37: features
B38: Operational/Client Work | C38: =COUNTIF(Master_Data_Features!AS:AS,"No") -> 40 | D38: features
B39: Artemis ARR Impact | C39: =_xlfn.SUMIFS(Master_Data_Features!K:K,Master_Data_Features!AS:AS,"Yes") -> 0
B40: Operational ARR Impact | C40: =_xlfn.SUMIFS(Master_Data_Features!K:K,Master_Data_Features!AS:AS,"No") -> 2530000
B42: PRDs Complete | C42: =COUNTIF(Master_Data_Features!AT:AT,"Complete") -> 7 | D42: out of 47
B43: Epics in JIRA | C43: =COUNTIF(Master_Data_Features!AU:AU,"Yes") -> 14 | D43: out of 47

Sheet PIVOT_Sales_View
B1: Priority_Tier | C1: All
B2: Quarter_Planned | C2: All
B3: Agent_Type | C3: All
D5: Values | E5: Current_Status
D6: Total ARR | G6: Feature Count | J6: Avg Completion % | M6: Total Total ARR | N6: Total Feature Count | O6: Total Avg Completion %
B7: Primary_Client | C7: Feature_Name | D7: (blank) | E7: In Progress | F7: Not Started | G7: (blank) | H7: In Progress | I7: Not Started | J7: (blank) | K7: In Progress | L7: Not Started
B8: Accenture
C9: Accenture Email Automation Deployment | D9: 1200000 | E9: 0 | F9: 0 | G9: 1 | H9: 0 | I9: 0 | J9: 0 | K9: 0 | L9: 0 | M9: 1200000 | N9: 1 | O9: 0
C10: Accenture Multi-Agent Orchestration | D10: 0 | E10: 0 | F10: 0 | G10: 1 | H10: 0 | I10: 0 | J10: 0 | K10: 0 | L10: 0 | M10: 0 | N10: 1 | O10: 0
B11: Accenture Total | D11: 1200000 | E11: 0 | F11: 0 | G11: 2 | H11: 0 | I11: 0 | J11: 0 | K11: 0 | L11: 0 | M11: 1200000 | N11: 2 | O11: 0
B12: Broadridge
C13: Broadridge Critical Bug Fix - Trade Processing | D13: 0 | E13: -500000 | F13: 0 | G13: 0 | H13: 1 | I13: 0 | J13: 0 | K13: 0.7 | L13: 0 | M13: -500000 | N13: 1 | O13: 0.7
C14: Broadridge Email Automation Workflow | D14: 500000 | E14: 0 | F14: 0 | G14: 1 | H14: 0 | I14: 0 | J14: 0 | K14: 0 | L14: 0 | M14: 500000 | N14: 1 | O14: 0
C15: Broadridge Trade Matching Engine Enhancement | D15: 0 | E15: 0 | F15: 0 | G15: 1 | H15: 0 | I15: 0 | J15: 0 | K15: 0 | L15: 0 | M15: 0 | N15: 1 | O15: 0
B16: Broadridge Total | D16: 500000 | E16: -500000 | F16: 0 | G16: 2 | H16: 1 | I16: 0 | J16: 0 | K16: 0.7 | L16: 0 | M16: 0 | N16: 3 | O16: 0.7
B17: DTCC
C18: DTCC Agent Onboarding - Core Reconciliation | D18: 0 | E18: 0 | F18: 0 | G18: 1 | H18: 0 | I18: 0 | J18: 0 | K18: 0 | L18: 0 | M18: 0 | N18: 1 | O18: 0
C19: DTCC Agent Onboarding - Trade Processing Phase 1 | D19: 750000 | E19: 0 | F19: 0 | G19: 1 | H19: 0 | I19: 0 | J19: 0.6 | K19: 0 | L19: 0 | M19: 750000 | N19: 1 | O19: 0.6
C20: DTCC Agent Onboarding - Trade Processing Phase 2 | D20: 0 | E20: 0 | F20: 0 | G20: 1 | H20: 0 | I20: 0 | J20: 0 | K20: 0 | L20: 0 | M20: 0 | N20: 1 | O20: 0
B21: DTCC Total | D21: 750000 | E21: 0 | F21: 0 | G21: 3 | H21: 0 | I21: 0 | J21: 0.6 | K21: 0 | L21: 0 | M21: 750000 | N21: 3 | O21: 0.6
B22: Internal
C23: DeepSee Service Fabric Internal Enhancements | D23: 0 | E23: 0 | F23: 0 | G23: 1 | H23: 0 | I23: 0 | J23: 0 | K23: 0 | L23: 0 | M23: 0 | N23: 1 | O23: 0
B24: Internal Total | D24: 0 | E24: 0 | F24: 0 | G24: 1 | H24: 0 | I24: 0 | J24: 0 | K24: 0 | L24: 0 | M24: 0 | N24: 1 | O24: 0
B25: JP Morgan
C26: JP Morgan Monthly Reconciliation Enhancement | D26: 0 | E26: 0 | F26: 0 | G26: 1 | H26: 0 | I26: 0 | J26: 0 | K26: 0 | L26: 0 | M26: 0 | N26: 1 | O26: 0
C27: JP Morgan Security Settlements Optimization | D27: 0 | E27: 0 | F27: 0 | G27: 1 | H27: 0 | I27: 0 | J27: 0 | K27: 0 | L27: 0 | M27: 0 | N27: 1 | O27: 0
B28: JP Morgan Total | D28: 0 | E28: 0 | F28: 0 | G28: 2 | H28: 0 | I28: 0 | J28: 0 | K28: 0 | L28: 0 | M28: 0 | N28: 2 | O28: 0
B29: Multiple
C30: Activity Tracing Across Agents | D30: 0 | E30: 0 | F30: 0 | G30: 1 | H30: 0 | I30: 0 | J30: 0 | K30: 0 | L30: 0 | M30: 0 | N30: 1 | O30: 0
C31: Agentic Card UI Implementation for 3rd Party Applications | D31: 0 | E31: 0 | F31: 0 | G31: 1 | H31: 0 | I31: 0 | J31: 0 | K31: 0 | L31: 0 | M31: 0 | N31: 1 | O31: 0
C32: Client Agent Interaction Enhancements | D32: 0 | E32: 0 | F32: 0 | G32: 1 | H32: 0 | I32: 0 | J32: 0 | K32: 0 | L32: 0 | M32: 0 | N32: 1 | O32: 0
C33: Core Reconciliation - Multi-System Support | D33: 0 | E33: 0 | F33: 0 | G33: 1 | H33: 0 | I33: 0 | J33: 0 | K33: 0 | L33: 0 | M33: 0 | N33: 1 | O33: 0
C34: DeepPilot - Financial Services Context Mining | D34: 0 | E34: 0 | F34: 0 | G34: 1 | H34: 0 | I34: 0 | J34: 0 | K34: 0 | L34: 0 | M34: 0 | N34: 1 | O34: 0
C35: DeepSee Service Fabric External Enhancements | D35: 0 | E35: 0 | F35: 0 | G35: 1 | H35: 0 | I35: 0 | J35: 0 | K35: 0 | L35: 0 | M35: 0 | N35: 1 | O35: 0
C36: Double-click to view dashboard messages | D36: 0 | E36: 0 | F36: 0 | G36: 1 | H36: 0 | I36: 0 | J36: 0 | K36: 0 | L36: 0 | M36: 0 | N36: 1 | O36: 0
C37: Email Automation - Response Generation Enhancement | D37: 0 | E37: 0 | F37: 0 | G37: 1 | H37: 0 | I37: 0 | J37: 0 | K37: 0 | L37: 0 | M37: 0 | N37: 1 | O37: 0
C38: Enhanced Agent Outcome Reasoning and Planning | D38: 0 | E38: 0 | F38: 0 | G38: 1 | H38: 0 | I38: 0 | J38: 0 | K38: 0 | L38: 0 | M38: 0 | N38: 1 | O38: 0
C39: Enhanced Integration with 3rd Party Applications - Outlook & Ops Console | D39: 0 | E39: 0 | F39: 0 | G39: 1 | H39: 0 | I39: 0 | J39: 0 | K39: 0 | L39: 0 | M39: 0 | N39: 1 | O39: 0
C40: Enhanced Testing Suite UI Implementation | D40: 0 | E40: 0 | F40: 0 | G40: 1 | H40: 0 | I40: 0 | J40: 0 | K40: 0 | L40: 0 | M40: 0 | N40: 1 | O40: 0
C41: Exception Prediction | D41: 0 | E41: 0 | F41: 0 | G41: 1 | H41: 0 | I41: 0 | J41: 0 | K41: 0 | L41: 0 | M41: 0 | N41: 1 | O41: 0
... C62: User configurable dashboards | D62: 0 | E62: 0 | F62: 0 | G62: 1 | H62: 0 | I62: 0 | J62: 0 | K62: 0 | L62: 0 | M62: 0 | N62: 1 | O62: 0
B63: Multiple Total | D63: 0 | E63: 0 | F63: 0 | G63: 33 | H63: 0 | I63: 0 | J63: 0 | K63: 0 | L63: 0 | M63: 0 | N63: 33 | O63: 0
B64: Regional Banks
C65: SSI Agent Deployment - Colony Bank | D65: 0 | E65: 200000 | F65: 0 | G65: 0 | H65: 1 | I65: 0 | J65: 0 | K65: 0.4 | L65: 0 | M65: 200000 | N65: 1 | O65: 0.4
C66: SSI Agent Deployment - Sunwest Bank | D66: 180000 | E66: 0 | F66: 0 | G66: 1 | H66: 0 | I66: 0 | J66: 0 | K66: 0 | L66: 0 | M66: 180000 | N66: 1 | O66: 0
C67: Vantage Bank Custom Reconciliation (POC) | D67: 0 | E67: 0 | F67: 200000 | G67: 0 | H67: 0 | I67: 1 | J67: 0 | K67: 0 | L67: 0 | M67: 200000 | N67: 1 | O67: 0
B68: Regional Banks Total | D68: 180000 | E68: 200000 | F68: 200000 | G68: 1 | H68: 1 | I68: 1 | J68: 0 | K68: 0.4 | L68: 0 | M68: 580000 | N68: 3 | O68: 0.4
B69: Grand Total | D69: 2630000 | E69: -300000 | F69: 200000 | G69: 44 | H69: 2 | I69: 1 | J69: 0.6 | K69: 0.55 | L69: 0 | M69: 2530000 | N69: 47 | O69: 0.56666667

Sheet PIVOT_Management_View
B1: Revenue_Type | C1: All
B2: Agent_Type | C2: All
B3: Primary_Client | C3: All
B4: Current_Status | C4: All
D6: Values | E6: Quarter_Planned
D7: Total ARR | H7: Weighted ARR | L7: Total Effort (Weeks) | P7: Avg Probability | T7: Total Total ARR | U7: Total Weighted ARR | V7: Total Total Effort (Weeks) | W7: Total Avg Probability
B8: Priority_Tier | C8: Feature_Name | D8: Q1 2026 | E8: Q2 2026 | F8: Q3 2026 | G8: Q4 2025 | H8: Q1 2026 | I8: Q2 2026 | J8: Q3 2026 | K8: Q4 2025 | L8: Q1 2026 | M8: Q2 2026 | N8: Q3 2026 | O8: Q4 2025 | P8: Q1 2026 | Q8: Q2 2026 | R8: Q3 2026 | S8: Q4 2025
B9: Tier 0: Emergency
C10: Broadridge Critical Bug Fix - Trade Processing | D10: 0 | E10: 0 | F10: 0 | G10: -500000 | H10: 0 | I10: 0 | J10: 0 | K10: -5000 | L10: 0 | M10: 0 | N10: 0 | O10: 1 | P10: 0 | Q10: 0 | R10: 0 | S10: 1 | T10: -500000 | U10: -5000 | V10: 1 | W10: 1
B11: Tier 0: Emergency Total | D11: 0 | E11: 0 | F11: 0 | G11: -500000 | H11: 0 | I11: 0 | J11: 0 | K11: -5000 | L11: 0 | M11: 0 | N11: 0 | O11: 1 | P11: 0 | Q11: 0 | R11: 0 | S11: 1 | T11: -500000 | U11: -5000 | V11: 1 | W11: 1
B12: Tier 1: Fast Track
C13: Accenture Email Automation Deployment | D13: 0 | E13: 0 | F13: 0 | G13: 1200000 | H13: 0 | I13: 0 | J13: 0 | K13: 12000 | L13: 0 | M13: 0 | N13: 0 | O13: 0 | P13: 0 | Q13: 0 | R13: 0 | S13: 1 | T13: 1200000 | U13: 12000 | V13: 0 | W13: 1
C14: Broadridge Email Automation Workflow | D14: 0 | E14: 0 | F14: 0 | G14: 500000 | H14: 0 | I14: 0 | J14: 0 | K14: 5000 | L14: 0 | M14: 0 | N14: 0 | O14: 0 | P14: 0 | Q14: 0 | R14: 0 | S14: 1 | T14: 500000 | U14: 5000 | V14: 0 | W14: 1
C15: DTCC Agent Onboarding - Trade Processing Phase 1 | D15: 0 | E15: 0 | F15: 0 | G15: 750000 | H15: 0 | I15: 0 | J15: 0 | K15: 7500 | L15: 0 | M15: 0 | N15: 0 | O15: 0 | P15: 0 | Q15: 0 | R15: 0 | S15: 1 | T15: 750000 | U15: 7500 | V15: 0 | W15: 1
C16: SSI Agent Deployment - Colony Bank | D16: 0 | E16: 0 | F16: 0 | G16: 200000 | H16: 0 | I16: 0 | J16: 0 | K16: 2000 | L16: 0 | M16: 0 | N16: 0 | O16: 6 | P16: 0 | Q16: 0 | R16: 0 | S16: 1 | T16: 200000 | U16: 2000 | V16: 6 | W16: 1
C17: SSI Agent Deployment - Sunwest Bank | D17: 180000 | E17: 0 | F17: 0 | G17: 0 | H17: 1440 | I17: 0 | J17: 0 | K17: 0 | L17: 0 | M17: 0 | N17: 0 | O17: 0 | P17: 0.8 | Q17: 0 | R17: 0 | S17: 0 | T17: 180000 | U17: 1440 | V17: 0 | W17: 0.8
C18: Vantage Bank Custom Reconciliation (POC) | D18: 200000 | E18: 0 | F18: 0 | G18: 0 | H18: 1000 | I18: 0 | J18: 0 | K18: 0 | L18: 12 | M18: 0 | N18: 0 | O18: 0 | P18: 0.5 | Q18: 0 | R18: 0 | S18: 0 | T18: 200000 | U18: 1000 | V18: 12 | W18: 0.5
B19: Tier 1: Fast Track Total | D19: 380000 | E19: 0 | F19: 0 | G19: 2650000 | H19: 2440 | I19: 0 | J19: 0 | K19: 26500 | L19: 12 | M19: 0 | N19: 0 | O19: 6 | P19: 0.65 | Q19: 0 | R19: 0 | S19: 1 | T19: 3030000 | U19: 28940 | V19: 18 | W19: 0.88333333
B20: Tier 4: Backlog
C21: Accenture Multi-Agent Orchestration | D21: 0 | E21: 0 | F21: 0 | G21: 0 | H21: 0 | I21: 0 | J21: 0 | K21: 0 | L21: 0 | M21: 0 | N21: 0 | O21: 0 | P21: 0 | Q21: 0 | R21: 0 | S21: 0 | T21: 0 | U21: 0 | V21: 0 | W21: 0
C22: Activity Tracing Across Agents | D22: 0 | E22: 0 | F22: 0 | G22: 0 | H22: 0 | I22: 0 | J22: 0 | K22: 0 | L22: 0 | M22: 0 | N22: 0 | O22: 0 | P22: 0 | Q22: 0 | R22: 0 | S22: 0 | T22: 0 | U22: 0 | V22: 0 | W22: 0
C23: Agentic Card UI Implementation for 3rd Party Applications | D23: 0 | E23: 0 | F23: 0 | G23: 0 | H23: 0 | I23: 0 | J23: 0 | K23: 0 | L23: 0 | M23: 0 | N23: 0 | O23: 0 | P23: 0 | Q23: 0 | R23: 0 | S23: 0 | T23: 0 | U23: 0 | V23: 0 | W23: 0
C24: Broadridge Trade Matching Engine Enhancement | D24: 0 | E24: 0 | F24: 0 | G24: 0 | H24: 0 | I24: 0 | J24: 0 | K24: 0 | L24: 0 | M24: 0 | N24: 0 | O24: 0 | P24: 0 | Q24: 0 | R24: 0 | S24: 0 | T24: 0 | U24: 0 | V24: 0 | W24: 0
C25: Client Agent Interaction Enhancements | D25: 0 | E25: 0 | F25: 0 | G25: 0 | H25: 0 | I25: 0 | J25: 0 | K25: 0 | L25: 0 | M25: 0 | N25: 0 | O25: 0 | P25: 0 | Q25: 0 | R25: 0 | S25: 0 | T25: 0 | U25: 0 | V25: 0 | W25: 0
C26: Core Reconciliation - Multi-System Support | D26: 0 | E26: 0 | F26: 0 | G26: 0 | H26: 0 | I26: 0 | J26: 0 | K26: 0 | L26: 0 | M26: 0 | N26: 0 | O26: 0 | P26: 0 | Q26: 0 | R26: 0 | S26: 0 | T26: 0 | U26: 0 | V26: 0 | W26: 0
C27: DeepPilot - Financial Services Context Mining | D27: 0 | E27: 0 | F27: 0 | G27: 0 | H27: 0 | I27: 0 | J27: 0 | K27: 0 | L27: 0 | M27: 0 | N27: 0 | O27: 0 | P27: 0 | Q27: 0 | R27: 0 | S27: 0 | T27: 0 | U27: 0 | V27: 0 | W27: 0
C28: DeepSee Service Fabric External Enhancements | D28: 0 | E28: 0 | F28: 0 | G28: 0 | H28: 0 | I28: 0 | J28: 0 | K28: 0 | L28: 0 | M28: 0 | N28: 0 | O28: 0 | P28: 0 | Q28: 0 | R28: 0 | S28: 0 | T28: 0 | U28: 0 | V28: 0 | W28: 0
C29: DeepSee Service Fabric Internal Enhancements | D29: 0 | E29: 0 | F29: 0 | G29: 0 | H29: 0 | I29: 0 | J29: 0 | K29: 0 | L29: 0 | M29: 0 | N29: 0 | O29: 0 | P29: 0 | Q29: 0 | R29: 0 | S29: 0 | T29: 0 | U29: 0 | V29: 0 | W29: 0
C30: Double-click to view dashboard messages | D30: 0 | E30: 0 | F30: 0 | G30: 0 | H30: 0 | I30: 0 | J30: 0 | K30: 0 | L30: 0 | M30: 0 | N30: 0 | O30: 0 | P30: 0 | Q30: 0 | R30: 0 | S30: 0 | T30: 0 | U30: 0 | V30: 0 | W30: 0
C31: DTCC Agent Onboarding - Core Reconciliation | D31: 0 | E31: 0 | F31: 0 | G31: 0 | H31: 0 | I31: 0 | J31: 0 | K31: 0 | L31: 0 | M31: 0 | N31: 0 | O31: 0 | P31: 0 | Q31: 0 | R31: 0 | S31: 0 | T31: 0 | U31: 0 | V31: 0 | W31: 0
C32: DTCC Agent Onboarding - Trade Processing Phase 2 | D32: 0 | E32: 0 | F32: 0 | G32: 0 | H32: 0 | I32: 0 | J32: 0 | K32: 0 | L32: 0 | M32: 0 | N32: 0 | O32: 0 | P32: 0 | Q32: 0 | R32: 0 | S32: 0 | T32: 0 | U32: 0 | V32: 0 | W32: 0
... C60: User configurable dashboards | D60: 0 | E60: 0 | F60: 0 | G60: 0 | H60: 0 | I60: 0 | J60: 0 | K60: 0 | L60: 0 | M60: 0 | N60: 0 | O60: 0 | P60: 0 | Q60: 0 | R60: 0 | S60: 0 | T60: 0 | U60: 0 | V60: 0 | W60: 0
B61: Tier 4: Backlog Total | D61: 0 | E61: 0 | F61: 0 | G61: 0 | H61: 0 | I61: 0 | J61: 0 | K61: 0 | L61: 0 | M61: 0 | N61: 0 | O61: 0 | P61: 0 | Q61: 0 | R61: 0 | S61: 0 | T61: 0 | U61: 0 | V61: 0 | W61: 0
B62: Grand Total | D62: 380000 | E62: 0 | F62: 0 | G62: 2150000 | H62: 2440 | I62: 0 | J62: 0 | K62: 21500 | L62: 12 | M62: 0 | N62: 0 | O62: 7 | P62: 0.65 | Q62: 0 | R62: 0 | S62: 1 | T62: 2530000 | U62: 23940 | V62: 19 | W62: 0.9

Sheet PIVOT_Engineering_View
B1: Priority_Tier | C1: All
B2: Current_Status | C2: All
B3: Quarter_Planned | C3: All
E5: Values | F5: Engineering_Complexity
E6: Total Effort (Weeks) | I6: Total JIRA Tickets | M6: Feature Count | Q6: Avg Priority Score | U6: Total Total Effort (Weeks) | V6: Total Total JIRA Tickets | W6: Total Feature Count | X6: Total Avg Priority Score
B7: Sprint_Assignment | C7: Team_Required | D7: Feature_Name | E7: (blank) | F7: High | G7: Medium | H7: Low | I7: (blank) | J7: High | K7: Medium | L7: Low | M7: (blank) | N7: High | O7: Medium | P7: Low | Q7: (blank) | R7: High | S7: Medium | T7: Low
B8: (blank)
C9: (blank)
D10: Accenture Multi-Agent Orchestration | E10: 0 | F10: 0 | G10: 0 | H10: 0 | I10: 0 | J10: 0 | K10: 0 | L10: 0 | M10: 1 | N10: 0 | O10: 0 | P10: 0 | Q10: 0 | R10: 0 | S10: 0 | T10: 0 | U10: 0 | V10: 0 | W10: 1 | X10: 0
D11: Activity Tracing Across Agents | E11: 0 | F11: 0 | G11: 0 | H11: 0 | I11: 0 | J11: 0 | K11: 0 | L11: 0 | M11: 1 | N11: 0 | O11: 0 | P11: 0 | Q11: 0 | R11: 0 | S11: 0 | T11: 0 | U11: 0 | V11: 0 | W11: 1 | X11: 0
D12: Agentic Card UI Implementation for 3rd Party Applications | E12: 0 | F12: 0 | G12: 0 | H12: 0 | I12: 0 | J12: 0 | K12: 0 | L12: 0 | M12: 1 | N12: 0 | O12: 0 | P12: 0 | Q12: 0 | R12: 0 | S12: 0 | T12: 0 | U12: 0 | V12: 0 | W12: 1 | X12: 0
D13: Broadridge Trade Matching Engine Enhancement | E13: 0 | F13: 0 | G13: 0 | H13: 0 | I13: 0 | J13: 0 | K13: 0 | L13: 0 | M13: 1 | N13: 0 | O13: 0 | P13: 0 | Q13: 0 | R13: 0 | S13: 0 | T13: 0 | U13: 0 | V13: 0 | W13: 1 | X13: 0
D14: Client Agent Interaction Enhancements | E14: 0 | F14: 0 | G14: 0 | H14: 0 | I14: 0 | J14: 0 | K14: 0 | L14: 0 | M14: 1 | N14: 0 | O14: 0 | P14: 0 | Q14: 0 | R14: 0 | S14: 0 | T14: 0 | U14: 0 | V14: 0 | W14: 1 | X14: 0
D15: Core Reconciliation - Multi-System Support | E15: 0 | F15: 0 | G15: 0 | H15: 0 | I15: 0 | J15: 0 | K15: 0 | L15: 0 | M15: 1 | N15: 0 | O15: 0 | P15: 0 | Q15: 0 | R15: 0 | S15: 0 | T15: 0 | U15: 0 | V15: 0 | W15: 1 | X15: 0
D16: DeepPilot - Financial Services Context Mining | E16: 0 | F16: 0 | G16: 0 | H16: 0 | I16: 0 | J16: 0 | K16: 0 | L16: 0 | M16: 1 | N16: 0 | O16: 0 | P16: 0 | Q16: 0 | R16: 0 | S16: 0 | T16: 0 | U16: 0 | V16: 0 | W16: 1 | X16: 0
D17: DeepSee Service Fabric External Enhancements | E17: 0 | F17: 0 | G17: 0 | H17: 0 | I17: 0 | J17: 0 | K17: 0 | L17: 0 | M17: 1 | N17: 0 | O17: 0 | P17: 0 | Q17: 0 | R17: 0 | S17: 0 | T17: 0 | U17: 0 | V17: 0 | W17: 1 | X17: 0
D18: DeepSee Service Fabric Internal Enhancements | E18: 0 | F18: 0 | G18: 0 | H18: 0 | I18: 0 | J18: 0 | K18: 0 | L18: 0 | M18: 1 | N18: 0 | O18: 0 | P18: 0 | Q18: 0 | R18: 0 | S18: 0 | T18: 0 | U18: 0 | V18: 0 | W18: 1 | X18: 0
D19: Double-click to view dashboard messages | E19: 0 | F19: 0 | G19: 0 | H19: 0 | I19: 0 | J19: 0 | K19: 0 | L19: 0 | M19: 1 | N19: 0 | O19: 0 | P19: 0 | Q19: 0 | R19: 0 | S19: 0 | T19: 0 | U19: 0 | V19: 0 | W19: 1 | X19: 0
D20: DTCC Agent Onboarding - Core Reconciliation | E20: 0 | F20: 0 | G20: 0 | H20: 0 | I20: 0 | J20: 0 | K20: 0 | L20: 0 | M20: 1 | N20: 0 | O20: 0 | P20: 0 | Q20: 0 | R20: 0 | S20: 0 | T20: 0 | U20: 0 | V20: 0 | W20: 1 | X20: 0
D21: DTCC Agent Onboarding - Trade Processing Phase 2 | E21: 0 | F21: 0 | G21: 0 | H21: 0 | I21: 0 | J21: 0 | K21: 0 | L21: 0 | M21: 1 | N21: 0 | O21: 0 | P21: 0 | Q21: 0 | R21: 0 | S21: 0 | T21: 0 | U21: 0 | V21: 0 | W21: 1 | X21: 0
... D49: User configurable dashboards | E49: 0 | F49: 0 | G49: 0 | H49: 0 | I49: 0 | J49: 0 | K49: 0 | L49: 0 | M49: 1 | N49: 0 | O49: 0 | P49: 0 | Q49: 0 | R49: 0 | S49: 0 | T49: 0 | U49: 0 | V49: 0 | W49: 1 | X49: 0
C50: (blank) Total | E50: 0 | F50: 0 | G50: 0 | H50: 0 | I50: 0 | J50: 0 | K50: 0 | L50: 0 | M50: 40 | N50: 0 | O50: 0 | P50: 0 | Q50: 0 | R50: 0 | S50: 0 | T50: 0 | U50: 0 | V50: 0 | W50: 40 | X50: 0
C51: Multiple Teams
D52: Accenture Email Automation Deployment | E52: 0 | F52: 0 | G52: 0 | H52: 0 | I52: 0 | J52: 0 | K52: 0 | L52: 0 | M52: 0 | N52: 0 | O52: 1 | P52: 0 | Q52: 0 | R52: 0 | S52: 0 | T52: 0 | U52: 0 | V52: 0 | W52: 1 | X52: 0
D53: DTCC Agent Onboarding - Trade Processing Phase 1 | E53: 0 | F53: 0 | G53: 0 | H53: 0 | I53: 0 | J53: 0 | K53: 0 | L53: 0 | M53: 0 | N53: 1 | O53: 0 | P53: 0 | Q53: 0 | R53: 0 | S53: 0 | T53: 0 | U53: 0 | V53: 0 | W53: 1 | X53: 0
C54: Multiple Teams Total | E54: 0 | F54: 0 | G54: 0 | H54: 0 | I54: 0 | J54: 0 | K54: 0 | L54: 0 | M54: 0 | N54: 1 | O54: 1 | P54: 0 | Q54: 0 | R54: 0 | S54: 0 | T54: 0 | U54: 0 | V54: 0 | W54: 2 | X54: 0
C55: Backend
D56: Broadridge Critical Bug Fix - Trade Processing | E56: 0 | F56: 0 | G56: 0 | H56: 1 | I56: 0 | J56: 0 | K56: 0 | L56: 0 | M56: 0 | N56: 0 | O56: 0 | P56: 1 | Q56: 0 | R56: 0 | S56: 0 | T56: -500000 | U56: 1 | V56: 0 | W56: 1 | X56: -500000
D57: Broadridge Email Automation Workflow | E57: 0 | F57: 0 | G57: 0 | H57: 0 | I57: 0 | J57: 0 | K57: 0 | L57: 0 | M57: 0 | N57: 0 | O57: 1 | P57: 0 | Q57: 0 | R57: 0 | S57: 0 | T57: 0 | U57: 0 | V57: 0 | W57: 1 | X57: 0
D58: SSI Agent Deployment - Colony Bank | E58: 0 | F58: 0 | G58: 6 | H58: 0 | I58: 0 | J58: 0 | K58: 0 | L58: 0 | M58: 0 | N58: 0 | O58: 1 | P58: 0 | Q58: 0 | R58: 0 | S58: 0 | T58: 0 | U58: 6 | V58: 0 | W58: 1 | X58: 0
D59: SSI Agent Deployment - Sunwest Bank | E59: 0 | F59: 0 | G59: 0 | H59: 0 | I59: 0 | J59: 0 | K59: 0 | L59: 0 | M59: 0 | N59: 0 | O59: 1 | P59: 0 | Q59: 0 | R59: 0 | S59: 0 | T59: 0 | U59: 0 | V59: 0 | W59: 1 | X59: 0
D60: Vantage Bank Custom Reconciliation (POC) | E60: 0 | F60: 12 | G60: 0 | H60: 0 | I60: 0 | J60: 0 | K60: 0 | L60: 0 | M60: 0 | N60: 1 | O60: 0 | P60: 0 | Q60: 0 | R60: 0 | S60: 0 | T60: 0 | U60: 12 | V60: 0 | W60: 1 | X60: 0
C61: Backend Total | E61: 0 | F61: 12 | G61: 6 | H61: 1 | I61: 0 | J61: 0 | K61: 0 | L61: 0 | M61: 0 | N61: 1 | O61: 3 | P61: 1 | Q61: 0 | R61: 0 | S61: 0 | T61: -500000 | U61: 19 | V61: 0 | W61: 5 | X61: -500000
B62: (blank) Total | E62: 0 | F62: 12 | G62: 6 | H62: 1 | I62: 0 | J62: 0 | K62: 0 | L62: 0 | M62: 40 | N62: 2 | O62: 4 | P62: 1 | Q62: 0 | R62: 0 | S62: 0 | T62: -500000 | U62: 19 | V62: 0 | W62: 47 | X62: -250000
B63: Grand Total | E63: 0 | F63: 12 | G63: 6 | H63: 1 | I63: 0 | J63: 0 | K63: 0 | L63: 0 | M63: 40 | N63: 2 | O63: 4 | P63: 1 | Q63: 0 | R63: 0 | S63: 0 | T63: -500000 | U63: 19 | V63: 0 | W63: 47 | X63: -250000

Sheet PIVOT_Product_Roadmap
B1: Primary_Client | C1: All
B2: Platform_vs_Custom | C2: All
B3: Current_Status | C3: All
E5: Values | F5: Priority_Tier
E6: Total ARR | H6: Total Effort (Weeks) | K6: Avg Replicability | N6: Total Total ARR | O6: Total Total Effort (Weeks) | P6: Total Avg Replicability
B7: Quarter_Planned | C7: Agent_Type | D7: Feature_Name | E7: Tier 0: Emergency | F7: Tier 1: Fast Track | G7: Tier 4: Backlog | H7: Tier 0: Emergency | I7: Tier 1: Fast Track | J7: Tier 4: Backlog | K7: Tier 0: Emergency | L7: Tier 1: Fast Track | M7: Tier 4: Backlog
B8: Q1 2026
C9: Core Reconciliation
D10: Core Reconciliation - Multi-System Support | E10: 0 | F10: 0 | G10: 0 | H10: 0 | I10: 0 | J10: 0 | K10: 0 | L10: 0 | M10: 5 | N10: 0 | O10: 0 | P10: 5
D11: DTCC Agent Onboarding - Core Reconciliation | E11: 0 | F11: 0 | G11: 0 | H11: 0 | I11: 0 | J11: 0 | K11: 0 | L11: 0 | M11: 3 | N11: 0 | O11: 0 | P11: 3
D12: JP Morgan Monthly Reconciliation Enhancement | E12: 0 | F12: 0 | G12: 0 | H12: 0 | I12: 0 | J12: 0 | K12: 0 | L12: 0 | M12: 3 | N12: 0 | O12: 0 | P12: 3
D13: Vantage Bank Custom Reconciliation (POC) | E13: 0 | F13: 200000 | G13: 0 | H13: 0 | I13: 12 | J13: 0 | K13: 0 | L13: 2 | M13: 0 | N13: 200000 | O13: 12 | P13: 2
C14: Core Reconciliation Total | E14: 0 | F14: 200000 | G14: 0 | H14: 0 | I14: 12 | J14: 0 | K14: 0 | L14: 2 | M14: 3.6666667 | N14: 200000 | O14: 12 | P14: 3.25
C15: Platform (All Agents)
D16: Accenture Multi-Agent Orchestration | E16: 0 | F16: 0 | G16: 0 | H16: 0 | I16: 0 | J16: 0 | K16: 0 | L16: 0 | M16: 4 | N16: 0 | O16: 0 | P16: 4
D17: Enhanced Agent Outcome Reasoning and Planning | E17: 0 | F17: 0 | G17: 0 | H17: 0 | I17: 0 | J17: 0 | K17: 0 | L17: 0 | M17: 5 | N17: 0 | O17: 0 | P17: 5
D18: Inference / Training speed improvements | E18: 0 | F18: 0 | G18: 0 | H18: 0 | I18: 0 | J18: 0 | K18: 0 | L18: 0 | M18: 5 | N18: 0 | O18: 0 | P18: 5
D19: Information Graph Enhanced Infrastructure | E19: 0 | F19: 0 | G19: 0 | H19: 0 | I19: 0 | J19: 0 | K19: 0 | L19: 0 | M19: 5 | N19: 0 | O19: 0 | P19: 5
D20: Simplified Agentic UI Implementation | E20: 0 | F20: 0 | G20: 0 | H20: 0 | I20: 0 | J20: 0 | K20: 0 | L20: 0 | M20: 5 | N20: 0 | O20: 0 | P20: 5
C21: Platform (All Agents) Total | E21: 0 | F21: 0 | G21: 0 | H21: 0 | I21: 0 | J21: 0 | K21: 0 | L21: 0 | M21: 4.8 | N21: 0 | O21: 0 | P21: 4.8
C22: Platform (Analytics)
D23: Activity Tracing Across Agents | E23: 0 | F23: 0 | G23: 0 | H23: 0 | I23: 0 | J23: 0 | K23: 0 | L23: 0 | M23: 5 | N23: 0 | O23: 0 | P23: 5
D24: Exception Prediction | E24: 0 | F24: 0 | G24: 0 | H24: 0 | I24: 0 | J24: 0 | K24: 0 | L24: 0 | M24: 5 | N24: 0 | O24: 0 | P24: 5
D25: Information Graph UI Design | E25: 0 | F25: 0 | G25: 0 | H25: 0 | I25: 0 | J25: 0 | K25: 0 | L25: 0 | M25: 5 | N25: 0 | O25: 0 | P25: 5
C26: Platform (Analytics) Total | E26: 0 | F26: 0 | G26: 0 | H26: 0 | I26: 0 | J26: 0 | K26: 0 | L26: 0 | M26: 5 | N26: 0 | O26: 0 | P26: 5
C27: Standing Settlement Instructions
D28: SSI - Real-time Data Validation | E28: 0 | F28: 0 | G28: 0 | H28: 0 | I28: 0 | J28: 0 | K28: 0 | L28: 0 | M28: 5 | N28: 0 | O28: 0 | P28: 5
D29: SSI Agent Deployment - Sunwest Bank | E29: 0 | F29: 180000 | G29: 0 | H29: 0 | I29: 0 | J29: 0 | K29: 0 | L29: 5 | M29: 0 | N29: 180000 | O29: 0 | P29: 5
C30: Standing Settlement Instructions Total | E30: 0 | F30: 180000 | G30: 0 | H30: 0 | I30: 0 | J30: 0 | K30: 0 | L30: 5 | M30: 5 | N30: 180000 | O30: 0 | P30: 5
C31: Trade Processing
D32: DTCC Agent Onboarding - Trade Processing Phase 2 | E32: 0 | F32: 0 | G32: 0 | H32: 0 | I32: 0 | J32: 0 | K32: 0 | L32: 0 | M32: 3 | N32: 0 | O32: 0 | P32: 3
D33: Trade Processing - 100% Accuracy Validation | E33: 0 | F33: 0 | G33: 0 | H33: 0 | I33: 0 | J33: 0 | K33: 0 | L33: 0 | M33: 5 | N33: 0 | O33: 0 | P33: 5
C34: Trade Processing Total | E34: 0 | F34: 0 | G34: 0 | H34: 0 | I34: 0 | J34: 0 | K34: 0 | L34: 0 | M34: 4 | N34: 0 | O34: 0 | P34: 4
B35: Q1 2026 Total | E35: 0 | F35: 380000 | G35: 0 | H35: 0 | I35: 12 | J35: 0 | K35: 0 | L35: 3.5 | M35: 4.5 | N35: 380000 | O35: 12 | P35: 4.375
B36: Q2 2026
C37: DeepPilot
D38: DeepPilot - Financial Services Context Mining | E38: 0 | F38: 0 | G38: 0 | H38: 0 | I38: 0 | J38: 0 | K38: 0 | L38: 0 | M38: 5 | N38: 0 | O38: 0 | P38: 5
C39: DeepPilot Total | E39: 0 | F39: 0 | G39: 0 | H39: 0 | I39: 0 | J39: 0 | K39: 0 | L39: 0 | M39: 5 | N39: 0 | O39: 0 | P39: 5
C40: Email Automation
D41: Email Automation - Response Generation Enhancement | E41: 0 | F41: 0 | G41: 0 | H41: 0 | I41: 0 | J41: 0 | K41: 0 | L41: 0 | M41: 5 | N41: 0 | O41: 0 | P41: 5
D42: Enhanced Integration with 3rd Party Applications - Outlook & Ops Console | E42: 0 | F42: 0 | G42: 0 | H42: 0 | I42: 0 | J42: 0 | K42: 0 | L42: 0 | M42: 4 | N42: 0 | O42: 0 | P42: 4
C43: Email Automation Total | E43: 0 | F43: 0 | G43: 0 | H43: 0 | I43: 0 | J43: 0 | K43: 0 | L43: 0 | M43: 4.5 | N43: 0 | O43: 0 | P43: 4.5
C44: Matching Engine
D45: Matching Engine - External Break Detection | E45: 0 | F45: 0 | G45: 0 | H45: 0 | I45: 0 | J45: 0 | K45: 0 | L45: 0 | M45: 4 | N45: 0 | O45: 0 | P45: 4
C46: Matching Engine Total | E46: 0 | F46: 0 | G46: 0 | H46: 0 | I46: 0 | J46: 0 | K46: 0 | L46: 0 | M46: 4 | N46: 0 | O46: 0 | P46: 4
C47: One View
D48: One View - Cross-System Integration | E48: 0 | F48: 0 | G48: 0 | H48: 0 | I48: 0 | J48: 0 | K48: 0 | L48: 0 | M48: 5 | N48: 0 | O48: 0 | P48: 5
C49: One View Total | E49: 0 | F49: 0 | G49: 0 | H49: 0 | I49: 0 | J49: 0 | K49: 0 | L49: 0 | M49: 5 | N49: 0 | O49: 0 | P49: 5
C50: Platform (All Agents)
D51: MCP Integration with 3rd Party Agents | E51: 0 | F51: 0 | G51: 0 | H51: 0 | I51: 0 | J51: 0 | K51: 0 | L51: 0 | M51: 5 | N51: 0 | O51: 0 | P51: 5
C52: Platform (All Agents) Total | E52: 0 | F52: 0 | G52: 0 | H52: 0 | I52: 0 | J52: 0 | K52: 0 | L52: 0 | M52: 5 | N52: 0 | O52: 0 | P52: 5
C53: Platform (Analytics)
D54: Information Graph UI Implementation | E54: 0 | F54: 0 | G54: 0 | H54: 0 | I54: 0 | J54: 0 | K54: 0 | L54: 0 | M54: 5 | N54: 0 | O54: 0 | P54: 5
D55: Process Mapping and Optimization Opportunities | E55: 0 | F55: 0 | G55: 0 | H55: 0 | I55: 0 | J55: 0 | K55: 0 | L55: 0 | M55: 5 | N55: 0 | O55: 0 | P55: 5
D56: Technologist and Model Review UI implementation | E56: 0 | F56: 0 | G56: 0 | H56: 0 | I56: 0 | J56: 0 | K56: 0 | L56: 0 | M56: 5 | N56: 0 | O56: 0 | P56: 5
D57: User configurable dashboards | E57: 0 | F57: 0 | G57: 0 | H57: 0 | I57: 0 | J57: 0 | K57: 0 | L57: 0 | M57: 5 | N57: 0 | O57: 0 | P57: 5
C58: Platform (Analytics) Total | E58: 0 | F58: 0 | G58: 0 | H58: 0 | I58: 0 | J58: 0 | K58: 0 | L58: 0 | M58: 5 | N58: 0 | O58: 0 | P58: 5
C59: Security Settlements
D60: JP Morgan Security Settlements Optimization | E60: 0 | F60: 0 | G60: 0 | H60: 0 | I60: 0 | J60: 0 | K60: 0 | L60: 0 | M60: 3 | N60: 0 | O60: 0 | P60: 3
D61: Security Settlements - Break Resolution Automation | E61: 0 | F61: 0 | G61: 0 | H61: 0 | I61: 0 | J61: 0 | K61: 0 | L61: 0 | M61: 5 | N61: 0 | O61: 0 | P61: 5
C62: Security Settlements Total | E62: 0 | F62: 0 | G62: 0 | H62: 0 | I62: 0 | J62: 0 | K62: 0 | L62: 0 | M62: 4 | N62: 0 | O62: 0 | P62: 4
B63: Q2 2026 Total | E63: 0 | F63: 0 | G63: 0 | H63: 0 | I63: 0 | J63: 0 | K63: 0 | L63: 0 | M63: 4.6666667 | N63: 0 | O63: 0 | P63: 4.6666667
B64: Q3 2026
C65: Loan Operations
D66: Loan Operations - Application Automation | E66: 0 | F66: 0 | G66: 0 | H66: 0 | I66: 0 | J66: 0 | K66: 0 | L66: 0 | M66: 4 | N66: 0 | O66: 0 | P66: 4
C67: Loan Operations Total | E67: 0 | F67: 0 | G67: 0 | H67: 0 | I67: 0 | J67: 0 | K67: 0 | L67: 0 | M67: 4 | N67: 0 | O67: 0 | P67: 4
C68: Platform (All Agents)
D69: Agentic Card UI Implementation for 3rd Party Applications | E69: 0 | F69: 0 | G69: 0 | H69: 0 | I69: 0 | J69: 0 | K69: 0 | L69: 0 | M69: 5 | N69: 0 | O69: 0 | P69: 5
D70: DeepSee Service Fabric External Enhancements | E70: 0 | F70: 0 | G70: 0 | H70: 0 | I70: 0 | J70: 0 | K70: 0 | L70: 0 | M70: 5 | N70: 0 | O70: 0 | P70: 5
D71: Enhanced Testing Suite UI Implementation | E71: 0 | F71: 0 | G71: 0 | H71: 0 | I71: 0 | J71: 0 | K71: 0 | L71: 0 | M71: 5 | N71: 0 | O71: 0 | P71: 5
D72: Integrated foreign language support | E72: 0 | F72: 0 | G72: 0 | H72: 0 | I72: 0 | J72: 0 | K72: 0 | L72: 0 | M72: 5 | N72: 0 | O72: 0 | P72: 5
C73: Platform (All Agents) Total | E73: 0 | F73: 0 | G73: 0 | H73: 0 | I73: 0 | J73: 0 | K73: 0 | L73: 0 | M73: 5 | N73: 0 | O73: 0 | P73: 5
C74: Platform (Analytics)
D75: Process variation highlights | E75: 0 | F75: 0 | G75: 0 | H75: 0 | I75: 0 | J75: 0 | K75: 0 | L75: 0 | M75: 5 | N75: 0 | O75: 0 | P75: 5
C76: Platform (Analytics) Total | E76: 0 | F76: 0 | G76: 0 | H76: 0 | I76: 0 | J76: 0 | K76: 0 | L76: 0 | M76: 5 | N76: 0 | O76: 0 | P76: 5
B77: Q3 2026 Total | E77: 0 | F77: 0 | G77: 0 | H77: 0 | I77: 0 | J77: 0 | K77: 0 | L77: 0 | M77: 4.8333333 | N77: 0 | O77: 0 | P77: 4.8333333
B78: Q4 2025
C79: Email Automation
D80: Accenture Email Automation Deployment | E80: 0 | F80: 1200000 | G80: 0 | H80: 0 | I80: 0 | J80: 0 | K80: 0 | L80: 4 | M80: 0 | N80: 1200000 | O80: 0 | P80: 4
D81: Broadridge Email Automation Workflow | E81: 0 | F81: 500000 | G81: 0 | H81: 0 | I81: 0 | J81: 0 | K81: 0 | L81: 3 | M81: 0 | N81: 500000 | O81: 0 | P81: 3
C82: Email Automation Total | E82: 0 | F82: 1700000 | G82: 0 | H82: 0 | I82: 0 | J82: 0 | K82: 0 | L82: 3.5 | M82: 0 | N82: 1700000 | O82: 0 | P82: 3.5
C83: Matching Engine
D84: Broadridge Trade Matching Engine Enhancement | E84: 0 | F84: 0 | G84: 0 | H84: 0 | I84: 0 | J84: 0 | K84: 0 | L84: 0 | M84: 2 | N84: 0 | O84: 0 | P84: 2
D85: Matching Engine UI | E85: 0 | F85: 0 | G85: 0 | H85: 0 | I85: 0 | J85: 0 | K85: 0 | L85: 0 | M85: 4 | N85: 0 | O85: 0 | P85: 4
C86: Matching Engine Total | E86: 0 | F86: 0 | G86: 0 | H86: 0 | I86: 0 | J86: 0 | K86: 0 | L86: 0 | M86: 3 | N86: 0 | O86: 0 | P86: 3
C87: Platform (All Agents)
D88: Client Agent Interaction Enhancements | E88: 0 | F88: 0 | G88: 0 | H88: 0 | I88: 0 | J88: 0 | K88: 0 | L88: 0 | M88: 5 | N88: 0 | O88: 0 | P88: 5
D89: DeepSee Service Fabric Internal Enhancements | E89: 0 | F89: 0 | G89: 0 | H89: 0 | I89: 0 | J89: 0 | K89: 0 | L89: 0 | M89: 5 | N89: 0 | O89: 0 | P89: 5
D90: LLM-Enhanced Extraction | E90: 0 | F90: 0 | G90: 0 | H90: 0 | I90: 0 | J90: 0 | K90: 0 | L90: 0 | M90: 5 | N90: 0 | O90: 0 | P90: 5
D91: Simplified Agentic UI Design | E91: 0 | F91: 0 | G91: 0 | H91: 0 | I91: 0 | J91: 0 | K91: 0 | L91: 0 | M91: 5 | N91: 0 | O91: 0 | P91: 5
C92: Platform (All Agents) Total | E92: 0 | F92: 0 | G92: 0 | H92: 0 | I92: 0 | J92: 0 | K92: 0 | L92: 0 | M92: 5 | N92: 0 | O92: 0 | P92: 5
C93: Platform (Analytics)
D94: Double-click to view dashboard messages | E94: 0 | F94: 0 | G94: 0 | H94: 0 | I94: 0 | J94: 0 | K94: 0 | L94: 0 | M94: 5 | N94: 0 | O94: 0 | P94: 5
D95: Retention Prediction UI | E95: 0 | F95: 0 | G95: 0 | H95: 0 | I95: 0 | J95: 0 | K95: 0 | L95: 0 | M95: 5 | N95: 0 | O95: 0 | P95: 5
C96: Platform (Analytics) Total | E96: 0 | F96: 0 | G96: 0 | H96: 0 | I96: 0 | J96: 0 | K96: 0 | L96: 0 | M96: 5 | N96: 0 | O96: 0 | P96: 5
C97: Standing Settlement Instructions
D98: SSI Agent Deployment - Colony Bank | E98: 0 | F98: 200000 | G98: 0 | H98: 0 | I98: 6 | J98: 0 | K98: 0 | L98: 5 | M98: 0 | N98: 200000 | O98: 6 | P98: 5
C99: Standing Settlement Instructions Total | E99: 0 | F99: 200000 | G99: 0 | H99: 0 | I99: 6 | J99: 0 | K99: 0 | L99: 5 | M99: 0 | N99: 200000 | O99: 6 | P99: 5
C100: Trade Processing
D101: Broadridge Critical Bug Fix - Trade Processing | E101: -500000 | F101: 0 | G101: 0 | H101: 1 | I101: 0 | J101: 0 | K101: 1 | L101: 0 | M101: 0 | N101: -500000 | O101: 1 | P101: 1
...

Sheet PIVOT_Strategic_vs_Operational
B2: STRATEGIC vs OPERATIONAL WORK - ARTEMIS PLATFORM FOCUS
B4: EXECUTIVE SUMMARY METRICS
B6: % Features: Artemis Focus | C6: =COUNTIF(Master_Data_Features!AS:AS,"Yes")/COUNTA(Master_Data_Features!B3:B49) -> 0.14893617
B7: Features with PRD Complete | C7: =COUNTIF(Master_Data_Features!AT:AT,"Complete") -> 7
B8: Features with Epic in JIRA | C8: =COUNTIF(Master_Data_Features!AU:AU,"Yes") -> 14
B9: Total ARR: Artemis Features | C9: =_xlfn.SUMIFS(Master_Data_Features!K:K,Master_Data_Features!AS:AS,"Yes") -> 0
B10: Quarter_Planned | C10: =_xlfn.SUMIFS(Master_Data_Features!K:K,Master_Data_Features!AS:AS,"No") -> All
B11: Primary_Client | C11: All
B12: Current_Status | C12: All
E14: Values | F14: PRD_Status
E15: Total ARR Impact | H15: Weighted ARR | K15: Total Effort (Weeks) | N15: Feature Count | Q15: Total Total ARR Impact | R15: Total Weighted ARR | S15: Total Total Effort (Weeks) | T15: Total Feature Count
B16: Artemis_Focus | C16: Priority_Tier | D16: Feature_Name | E16: Complete | F16: In Progress | G16: Not Started | H16: Complete | I16: In Progress | J16: Not Started | K16: Complete | L16: In Progress | M16: Not Started | N16: Complete | O16: In Progress | P16: Not Started
B17: No
C18: Tier 0: Emergency
D19: Broadridge Critical Bug Fix - Trade Processing | E19: -500000 | F19: 0 | G19: 0 | H19: -5000 | I19: 0 | J19: 0 | K19: 1 | L19: 0 | M19: 0 | N19: 1 | O19: 0 | P19: 0 | Q19: -500000 | R19: -5000 | S19: 1 | T19: 1
C20: Tier 0: Emergency Total | E20: -500000 | F20: 0 | G20: 0 | H20: -5000 | I20: 0 | J20: 0 | K20: 1 | L20: 0 | M20: 0 | N20: 1 | O20: 0 | P20: 0 | Q20: -500000 | R20: -5000 | S20: 1 | T20: 1
C21: Tier 1: Fast Track
D22: Accenture Email Automation Deployment | E22: 1200000 | F22: 0 | G22: 0 | H22: 12000 | I22: 0 | J22: 0 | K22: 0 | L22: 0 | M22: 0 | N22: 1 | O22: 0 | P22: 0 | Q22: 1200000 | R22: 12000 | S22: 0 | T22: 1
D23: Broadridge Email Automation Workflow | E23: 500000 | F23: 0 | G23: 0 | H23: 5000 | I23: 0 | J23: 0 | K23: 0 | L23: 0 | M23: 0 | N23: 1 | O23: 0 | P23: 0 | Q23: 500000 | R23: 5000 | S23: 0 | T23: 1
D24: DTCC Agent Onboarding - Trade Processing Phase 1 | E24: 750000 | F24: 0 | G24: 0 | H24: 7500 | I24: 0 | J24: 0 | K24: 0 | L24: 0 | M24: 0 | N24: 1 | O24: 0 | P24: 0 | Q24: 750000 | R24: 7500 | S24: 0 | T24: 1
D25: SSI Agent Deployment - Colony Bank | E25: 200000 | F25: 0 | G25: 0 | H25: 2000 | I25: 0 | J25: 0 | K25: 6 | L25: 0 | M25: 0 | N25: 1 | O25: 0 | P25: 0 | Q25: 200000 | R25: 2000 | S25: 6 | T25: 1
D26: SSI Agent Deployment - Sunwest Bank | E26: 180000 | F26: 0 | G26: 0 | H26: 1440 | I26: 0 | J26: 0 | K26: 0 | L26: 0 | M26: 0 | N26: 1 | O26: 0 | P26: 0 | Q26: 180000 | R26: 1440 | S26: 0 | T26: 1
D27: Vantage Bank Custom Reconciliation (POC) | E27: 200000 | F27: 0 | G27: 0 | H27: 1000 | I27: 0 | J27: 0 | K27: 12 | L27: 0 | M27: 0 | N27: 1 | O27: 0 | P27: 0 | Q27: 200000 | R27: 1000 | S27: 12 | T27: 1
C28: Tier 1: Fast Track Total | E28: 3030000 | F28: 0 | G28: 0 | H28: 28940 | I28: 0 | J28: 0 | K28: 18 | L28: 0 | M28: 0 | N28: 6 | O28: 0 | P28: 0 | Q28: 3030000 | R28: 28940 | S28: 18 | T28: 6
C29: Tier 4: Backlog
D30: Accenture Multi-Agent Orchestration | E30: 0 | F30: 0 | G30: 0 | H30: 0 | I30: 0 | J30: 0 | K30: 0 | L30: 0 | M30: 0 | N30: 0 | O30: 0 | P30: 1 | Q30: 0 | R30: 0 | S30: 0 | T30: 1
D31: Activity Tracing Across Agents | E31: 0 | F31: 0 | G31: 0 | H31: 0 | I31: 0 | J31: 0 | K31: 0 | L31: 0 | M31: 0 | N31: 0 | O31: 0 | P31: 1 | Q31: 0 | R31: 0 | S31: 0 | T31: 1
D32: Agentic Card UI Implementation for 3rd Party Applications | E32: 0 | F32: 0 | G32: 0 | H32: 0 | I32: 0 | J32: 0 | K32: 0 | L32: 0 | M32: 0 | N32: 0 | O32: 0 | P32: 1 | Q32: 0 | R32: 0 | S32: 0 | T32: 1
D33: Broadridge Trade Matching Engine Enhancement | E33: 0 | F33: 0 | G33: 0 | H33: 0 | I33: 0 | J33: 0 | K33: 0 | L33: 0 | M33: 0 | N33: 0 | O33: 0 | P33: 1 | Q33: 0 | R33: 0 | S33: 0 | T33: 1
D34: Client Agent Interaction Enhancements | E34: 0 | F34: 0 | G34: 0 | H34: 0 | I34: 0 | J34: 0 | K34: 0 | L34: 0 | M34: 0 | N34: 0 | O34: 0 | P34: 1 | Q34: 0 | R34: 0 | S34: 0 | T34: 1
D35: Core Reconciliation - Multi-System Support | E35: 0 | F35: 0 | G35: 0 | H35: 0 | I35: 0 | J35: 0 | K35: 0 | L35: 0 | M35: 0 | N35: 0 | O35: 0 | P35: 1 | Q35: 0 | R35: 0 | S35: 0 | T35: 1
D36: DeepPilot - Financial Services Context Mining | E36: 0 | F36: 0 | G36: 0 | H36: 0 | I36: 0 | J36: 0 | K36: 0 | L36: 0 | M36: 0 | N36: 0 | O36: 0 | P36: 1 | Q36: 0 | R36: 0 | S36: 0 | T36: 1
D37: DeepSee Service Fabric Internal Enhancements | E37: 0 | F37: 0 | G37: 0 | H37: 0 | I37: 0 | J37: 0 | K37: 0 | L37: 0 | M37: 0 | N37: 0 | O37: 0 | P37: 1 | Q37: 0 | R37: 0 | S37: 0 | T37: 1
D38: Double-click to view dashboard messages | E38: 0 | F38: 0 | G38: 0 | H38: 0 | I38: 0 | J38: 0 | K38: 0 | L38: 0 | M38: 0 | N38: 0 | O38: 0 | P38: 1 | Q38: 0 | R38: 0 | S38: 0 | T38: 1
D39: DTCC Agent Onboarding - Core Reconciliation | E39: 0 | F39: 0 | G39: 0 | H39: 0 | I39: 0 | J39: 0 | K39: 0 | L39: 0 | M39: 0 | N39: 0 | O39: 0 | P39: 1 | Q39: 0 | R39: 0 | S39: 0 | T39: 1
D40: DTCC Agent Onboarding - Trade Processing Phase 2 | E40: 0 | F40: 0 | G40: 0 | H40: 0 | I40: 0 | J40: 0 | K40: 0 | L40: 0 | M40: 0 | N40: 0 | O40: 0 | P40: 1 | Q40: 0 | R40: 0 | S40: 0 | T40: 1
D41: Email Automation - Response Generation Enhancement | E41: 0 | F41: 0 | G41: 0 | H41: 0 | I41: 0 | J41: 0 | K41: 0 | L41: 0 | M41: 0 | N41: 0 | O41: 0 | P41: 1 | Q41: 0 | R41: 0 | S41: 0 | T41: 1
... D62: User configurable dashboards | E62: 0 | F62: 0 | G62: 0 | H62: 0 | I62: 0 | J62: 0 | K62: 0 | L62: 0 | M62: 0 | N62: 0 | O62: 0 | P62: 1 | Q62: 0 | R62: 0 | S62: 0 | T62: 1
C63: Tier 4: Backlog Total | E63: 0 | F63: 0 | G63: 0 | H63: 0 | I63: 0 | J63: 0 | K63: 0 | L63: 0 | M63: 0 | N63: 0 | O63: 0 | P63: 33 | Q63: 0 | R63: 0 | S63: 0 | T63: 33
B64: No Total | E64: 2530000 | F64: 0 | G64: 0 | H64: 23940 | I64: 0 | J64: 0 | K64: 19 | L64: 0 | M64: 0 | N64: 7 | O64: 0 | P64: 33 | Q64: 2530000 | R64: 23940 | S64: 19 | T64: 40
B65: Yes
C66: Tier 4: Backlog
D67: DeepSee Service Fabric External Enhancements | E67: 0 | F67: 0 | G67: 0 | H67: 0 | I67: 0 | J67: 0 | K67: 0 | L67: 0 | M67: 0 | N67: 0 | O67: 1 | P67: 0 | Q67: 0 | R67: 0 | S67: 0 | T67: 1
D68: Enhanced Agent Outcome Reasoning and Planning | E68: 0 | F68: 0 | G68: 0 | H68: 0 | I68: 0 | J68: 0 | K68: 0 | L68: 0 | M68: 0 | N68: 0 | O68: 1 | P68: 0 | Q68: 0 | R68: 0 | S68: 0 | T68: 1
D69: Inference / Training speed improvements | E69: 0 | F69: 0 | G69: 0 | H69: 0 | I69: 0 | J69: 0 | K69: 0 | L69: 0 | M69: 0 | N69: 0 | O69: 1 | P69: 0 | Q69: 0 | R69: 0 | S69: 0 | T69: 1
D70: Information Graph Enhanced Infrastructure | E70: 0 | F70: 0 | G70: 0 | H70: 0 | I70: 0 | J70: 0 | K70: 0 | L70: 0 | M70: 0 | N70: 0 | O70: 1 | P70: 0 | Q70: 0 | R70: 0 | S70: 0 | T70: 1
D71: Integrated foreign language support | E71: 0 | F71: 0 | G71: 0 | H71: 0 | I71: 0 | J71: 0 | K71: 0 | L71: 0 | M71: 0 | N71: 0 | O71: 1 | P71: 0 | Q71: 0 | R71: 0 | S71: 0 | T71: 1
D72: LLM-Enhanced Extraction | E72: 0 | F72: 0 | G72: 0 | H72: 0 | I72: 0 | J72: 0 | K72: 0 | L72: 0 | M72: 0 | N72: 0 | O72: 1 | P72: 0 | Q72: 0 | R72: 0 | S72: 0 | T72: 1
D73: Simplified Agentic UI Design | E73: 0 | F73: 0 | G73: 0 | H73: 0 | I73: 0 | J73: 0 | K73: 0 | L73: 0 | M73: 0 | N73: 0 | O73: 1 | P73: 0 | Q73: 0 | R73: 0 | S73: 0 | T73: 1
C74: Tier 4: Backlog Total | E74: 0 | F74: 0 | G74: 0 | H74: 0 | I74: 0 | J74: 0 | K74: 0 | L74: 0 | M74: 0 | N74: 0 | O74: 7 | P74: 0 | Q74: 0 | R74: 0 | S74: 0 | T74: 7
B75: Yes Total | E75: 0 | F75: 0 | G75: 0 | H75: 0 | I75: 0 | J75: 0 | K75: 0 | L75: 0 | M75: 0 | N75: 0 | O75: 7 | P75: 0 | Q75: 0 | R75: 0 | S75: 0 | T75: 7
B76: Grand Total | E76: 2530000 | F76: 0 | G76: 0 | H76: 23940 | I76: 0 | J76: 0 | K76: 19 | L76: 0 | M76: 0 | N76: 7 | O76: 7 | P76: 33 | Q76: 2530000 | R76: 23940 | S76: 19 | T76: 47

Sheet JIRA_Summary
B2: JIRA TICKETS SUMMARY - 6 ACTIVE PROJECTS
B4: TICKETS BY PROJECT | G4: TICKETS BY STATUS
B6: project_key | C6: jira_category | D6: Ticket Count | G6: jira_status | H6: Ticket Count
B7: BACK | G7: At Risk | H7: 10
C8: Back End Development | D8: 804 | G8: Backlog | H8: 240
B9: BACK Total | D9: 804 | G9: Blocked | H9: 16
B10: CI | G10: Canceled | H10: 591
C11: Core-Infrastructure | D11: 549 | G11: Closed | H11: 12
B12: CI Total | D12: 549 | G12: Code Review | H12: 8
B13: FB | G13: Completed | H13: 82
C14: FILBERT | D14: 367 | G14: Discovery | H14: 1
B15: FB Total | D15: 367 | G15: In Progress | H15: 89
B16: PR | G16: In Testing | H16: 1
C17: Product Roadmap | D17: 526 | G17: New | H17: 44
B18: PR Total | D18: 526 | G18: On Track | H18: 8
B19: SC | G19: Planning | H19: 82
C20: Security & Compliance | D20: 236 | G20: To Do | H20: 1180
B21: SC Total | D21: 236 | G21: Waiting for approval | H21: 299
B22: UI | G22: Grand Total | H22: 2663
C23: Front End Development | D23: 181
B24: UI Total | D24: 181
B25: Grand Total | D25: 2663
